<?xml version="1.0" encoding="UTF-8" standalone="no"?>
<raConfiguration version="7">
  <generalSettings>
    <option key="#Board#" value="board.ra6t2mck" />
    <option key="CPU" value="RA6T2" />
    <option key="#TargetName#" value="R7FA6T2BD3CFP" />
    <option key="#TargetARCHITECTURE#" value="cortex-m33" />
    <option key="#DeviceCommand#" value="R7FA6T2BD" />
    <option key="#RTOS#" value="_none" />
    <option key="#pinconfiguration#" value="R7FA6T2BD3CFP.pincfg" />
    <option key="#FSPVersion#" value="6.2.0" />
    <option key="#ConfigurationFragments#" value="Renesas##BSP##Board##ra6t2_mck##" />
    <option key="#SELECTED_TOOLCHAIN#" value="gcc-arm-embedded" />
    <option key="#ToolchainVersion#" value="13.2.1.arm-13-7" />
  </generalSettings>
  <raBspConfiguration>
    <config id="config.bsp.ra6t2.R7FA6T2BD3CFP">
      <property id="config.bsp.part_number" value="config.bsp.part_number.value" />
      <property id="config.bsp.rom_size_bytes" value="config.bsp.rom_size_bytes.value" />
      <property id="config.bsp.rom_size_bytes_hidden" value="524288" />
      <property id="config.bsp.ram_size_bytes" value="config.bsp.ram_size_bytes.value" />
      <property id="config.bsp.data_flash_size_bytes" value="config.bsp.data_flash_size_bytes.value" />
      <property id="config.bsp.package_style" value="config.bsp.package_style.value" />
      <property id="config.bsp.package_pins" value="config.bsp.package_pins.value" />
    </config>
    <config id="config.bsp.ra6t2">
      <property id="config.bsp.series" value="config.bsp.series.value" />
    </config>
    <config id="config.bsp.ra6t2.fsp">
      <property id="config.bsp.fsp.tz.exception_response" value="config.bsp.fsp.tz.exception_response.nmi" />
      <property id="config.bsp.fsp.tz.cmsis.bfhfnmins" value="config.bsp.fsp.tz.cmsis.bfhfnmins.secure" />
      <property id="config.bsp.fsp.tz.cmsis.sysresetreqs" value="config.bsp.fsp.tz.cmsis.sysresetreqs.secure_only" />
      <property id="config.bsp.fsp.tz.cmsis.s_priority_boost" value="config.bsp.fsp.tz.cmsis.s_priority_boost.disabled" />
      <property id="config.bsp.fsp.tz.csar" value="config.bsp.fsp.tz.csar.both" />
      <property id="config.bsp.fsp.tz.rstsar" value="config.bsp.fsp.tz.rstsar.both" />
      <property id="config.bsp.fsp.tz.sramsar.sramprcr" value="config.bsp.fsp.tz.sramsar.sramprcr.both" />
      <property id="config.bsp.fsp.tz.sramsar.sramecc" value="config.bsp.fsp.tz.sramsar.sramecc.both" />
      <property id="config.bsp.fsp.tz.stbramsar" value="config.bsp.fsp.tz.stbramsar.both" />
      <property id="config.bsp.fsp.tz.bussara" value="config.bsp.fsp.tz.bussara.both" />
      <property id="config.bsp.fsp.tz.bussarb" value="config.bsp.fsp.tz.bussarb.both" />
      <property id="config.bsp.fsp.cache_line_size" value="config.bsp.fsp.cache_line_size.32" />
      <property id="config.bsp.fsp.OFS0.iwdt_start_mode" value="config.bsp.fsp.OFS0.iwdt_start_mode.disabled" />
      <property id="config.bsp.fsp.OFS0.iwdt_timeout" value="config.bsp.fsp.OFS0.iwdt_timeout.2048" />
      <property id="config.bsp.fsp.OFS0.iwdt_divisor" value="config.bsp.fsp.OFS0.iwdt_divisor.128" />
      <property id="config.bsp.fsp.OFS0.iwdt_window_end" value="config.bsp.fsp.OFS0.iwdt_window_end.0" />
      <property id="config.bsp.fsp.OFS0.iwdt_window_start" value="config.bsp.fsp.OFS0.iwdt_window_start.100" />
      <property id="config.bsp.fsp.OFS0.iwdt_reset_interrupt" value="config.bsp.fsp.OFS0.iwdt_reset_interrupt.Reset" />
      <property id="config.bsp.fsp.OFS0.iwdt_stop_control" value="config.bsp.fsp.OFS0.iwdt_stop_control.stops" />
      <property id="config.bsp.fsp.OFS0.wdt_start_mode" value="config.bsp.fsp.OFS0.wdt_start_mode.register" />
      <property id="config.bsp.fsp.OFS0.wdt_timeout" value="config.bsp.fsp.OFS0.wdt_timeout.16384" />
      <property id="config.bsp.fsp.OFS0.wdt_divisor" value="config.bsp.fsp.OFS0.wdt_divisor.128" />
      <property id="config.bsp.fsp.OFS0.wdt_window_end" value="config.bsp.fsp.OFS0.wdt_window_end.0" />
      <property id="config.bsp.fsp.OFS0.wdt_window_start" value="config.bsp.fsp.OFS0.wdt_window_start.100" />
      <property id="config.bsp.fsp.OFS0.wdt_reset_interrupt" value="config.bsp.fsp.OFS0.wdt_reset_interrupt.Reset" />
      <property id="config.bsp.fsp.OFS0.wdt_stop_control" value="config.bsp.fsp.OFS0.wdt_stop_control.stops" />
      <property id="config.bsp.fsp.OFS1.voltage_detection0.start" value="config.bsp.fsp.OFS1.voltage_detection0.start.disabled" />
      <property id="config.bsp.fsp.OFS1.voltage_detection0_level" value="config.bsp.fsp.OFS1.voltage_detection0_level.280" />
      <property id="config.bsp.fsp.OFS1.hoco_osc" value="config.bsp.fsp.OFS1.hoco_osc.disabled" />
      <property id="config.bsp.fsp.OFS1.PGA0_pseudo_differential_input" value="config.bsp.fsp.OFS1.PGA0_pseudo_differential_input.disabled" />
      <property id="config.bsp.fsp.OFS1.PGA1_pseudo_differential_input" value="config.bsp.fsp.OFS1.PGA1_pseudo_differential_input.disabled" />
      <property id="config.bsp.fsp.OFS1.PGA2_pseudo_differential_input" value="config.bsp.fsp.OFS1.PGA2_pseudo_differential_input.disabled" />
      <property id="config.bsp.fsp.OFS1.PGA3_pseudo_differential_input" value="config.bsp.fsp.OFS1.PGA3_pseudo_differential_input.disabled" />
      <property id="config.bsp.fsp.BPS.BPS0" value="" />
      <property id="config.bsp.fsp.PBPS.PBPS0" value="" />
      <property id="config.bsp.fsp.hoco_fll" value="config.bsp.fsp.hoco_fll.disabled" />
      <property id="config.bsp.fsp.tfu_mathlib" value="config.bsp.fsp.tfu_mathlib.enabled" />
      <property id="config.bsp.common.main_osc_wait" value="config.bsp.common.main_osc_wait.wait_8163" />
      <property id="config.bsp.fsp.mcu.adc.max_freq_hz" value="50000000" />
      <property id="config.bsp.fsp.mcu.sci_b_uart.max_baud" value="20000000" />
      <property id="config.bsp.fsp.mcu.sci_b_uart.ctspen_channels" value="0x021F" />
      <property id="config.bsp.fsp.mcu.adc.sample_and_hold" value="0" />
      <property id="config.bsp.fsp.mcu.sci_spi.max_bitrate" value="25000000" />
      <property id="config.bsp.fsp.mcu.spi.max_bitrate" value="50000000" />
      <property id="config.bsp.fsp.mcu.iic_master.rate.rate_fastplus" value="1" />
      <property id="config.bsp.fsp.mcu.gpt.pin_count_source_channels" value="0x000F" />
      <property id="config.bsp.fsp.mcu.canfd.num_channels" value="1" />
      <property id="config.bsp.fsp.mcu.canfd.rx_fifos" value="2" />
      <property id="config.bsp.fsp.mcu.canfd.buffer_ram" value="1216" />
      <property id="config.bsp.fsp.mcu.canfd.afl_rules" value="32" />
      <property id="config.bsp.fsp.mcu.canfd.max_data_rate_hz" value="5" />
    </config>
    <config id="config.bsp.ra">
      <property id="config.bsp.common.main" value="0x400" />
      <property id="config.bsp.common.heap" value="0x400" />
      <property id="config.bsp.common.vcc" value="3300" />
      <property id="config.bsp.common.checking" value="config.bsp.common.checking.enabled" />
      <property id="config.bsp.common.assert" value="config.bsp.common.assert.none" />
      <property id="config.bsp.common.error_log" value="config.bsp.common.error_log.none" />
      <property id="config.bsp.common.soft_reset" value="config.bsp.common.soft_reset.disabled" />
      <property id="config.bsp.common.main_osc_populated" value="config.bsp.common.main_osc_populated.enabled" />
      <property id="config.bsp.common.pfs_protect" value="config.bsp.common.pfs_protect.enabled" />
      <property id="config.bsp.common.c_runtime_init" value="config.bsp.common.c_runtime_init.enabled" />
      <property id="config.bsp.common.early_init" value="config.bsp.common.early_init.disabled" />
      <property id="config.bsp.common.main_osc_clock_source" value="config.bsp.common.main_osc_clock_source.crystal" />
      <property id="config.bsp.common.subclock_populated" value="config.bsp.common.subclock_populated.disabled" />
      <property id="config.bsp.common.subclock_drive" value="config.bsp.common.subclock_drive.standard" />
      <property id="config.bsp.common.subclock_stabilization_ms" value="1000" />
    </config>
  </raBspConfiguration>
  <raClockConfiguration>
    <node id="board.clock.xtal.freq" mul="10000000" option="_edit" />
    <node id="board.clock.hoco.freq" option="board.clock.hoco.freq.20m" />
    <node id="board.clock.loco.freq" option="board.clock.loco.freq.32768" />
    <node id="board.clock.moco.freq" option="board.clock.moco.freq.8m" />
    <node id="board.clock.pll.source" option="board.clock.pll.source.xtal" />
    <node id="board.clock.pll.div" option="board.clock.pll.div.1" />
    <node id="board.clock.pll.mul" option="board.clock.pll.mul.240" />
    <node id="board.clock.pll.display" option="board.clock.pll.display.value" />
    <node id="board.clock.pll2.source" option="board.clock.pll2.source.disabled" />
    <node id="board.clock.pll2.div" option="board.clock.pll2.div.1" />
    <node id="board.clock.pll2.mul" option="board.clock.pll2.mul.100" />
    <node id="board.clock.pll2.display" option="board.clock.pll2.display.value" />
    <node id="board.clock.clock.source" option="board.clock.clock.source.pll" />
    <node id="board.clock.clkout.source" option="board.clock.clkout.source.disabled" />
    <node id="board.clock.scispiclk.source" option="board.clock.scispiclk.source.disabled" />
    <node id="board.clock.canfdclk.source" option="board.clock.canfdclk.source.disabled" />
    <node id="board.clock.gptclk.source" option="board.clock.gptclk.source.disabled" />
    <node id="board.clock.iicclk.source" option="board.clock.iicclk.source.disabled" />
    <node id="board.clock.iclk.div" option="board.clock.iclk.div.1" />
    <node id="board.clock.pclka.div" option="board.clock.pclka.div.2" />
    <node id="board.clock.pclkb.div" option="board.clock.pclkb.div.4" />
    <node id="board.clock.pclkc.div" option="board.clock.pclkc.div.4" />
    <node id="board.clock.pclkd.div" option="board.clock.pclkd.div.2" />
    <node id="board.clock.fclk.div" option="board.clock.fclk.div.4" />
    <node id="board.clock.clkout.div" option="board.clock.clkout.div.1" />
    <node id="board.clock.scispiclk.div" option="board.clock.scispiclk.div.2" />
    <node id="board.clock.canfdclk.div" option="board.clock.canfdclk.div.6" />
    <node id="board.clock.gptclk.div" option="board.clock.gptclk.div.2" />
    <node id="board.clock.iicclk.div" option="board.clock.iicclk.div.1" />
    <node id="board.clock.iclk.display" option="board.clock.iclk.display.value" />
    <node id="board.clock.pclka.display" option="board.clock.pclka.display.value" />
    <node id="board.clock.pclkb.display" option="board.clock.pclkb.display.value" />
    <node id="board.clock.pclkc.display" option="board.clock.pclkc.display.value" />
    <node id="board.clock.pclkd.display" option="board.clock.pclkd.display.value" />
    <node id="board.clock.fclk.display" option="board.clock.fclk.display.value" />
    <node id="board.clock.clkout.display" option="board.clock.clkout.display.value" />
    <node id="board.clock.scispiclk.display" option="board.clock.scispiclk.display.value" />
    <node id="board.clock.canfdclk.display" option="board.clock.canfdclk.display.value" />
    <node id="board.clock.gptclk.display" option="board.clock.gptclk.display.value" />
    <node id="board.clock.iicclk.display" option="board.clock.iicclk.display.value" />
  </raClockConfiguration>
  <raComponentSelection>
    <component apiversion="" class="Common" condition="" group="all" subgroup="fsp_common" variant="" vendor="Renesas" version="6.2.0">
      <description>Board Support Package Common Files</description>
      <originalPack>Renesas.RA.6.2.0.pack</originalPack>
    </component>
    <component apiversion="" class="HAL Drivers" condition="" group="all" subgroup="r_adc_b" variant="" vendor="Renesas" version="6.2.0">
      <description>A/D Converter</description>
      <originalPack>Renesas.RA.6.2.0.pack</originalPack>
    </component>
    <component apiversion="" class="HAL Drivers" condition="" group="all" subgroup="r_ioport" variant="" vendor="Renesas" version="6.2.0">
      <description>I/O Port</description>
      <originalPack>Renesas.RA.6.2.0.pack</originalPack>
    </component>
    <component apiversion="" class="BSP" condition="" group="Board" subgroup="ra6t2_mck" variant="" vendor="Renesas" version="6.2.0">
      <description>MCK-RA6T2 Board Support Files</description>
      <originalPack>Renesas.RA_board_ra6t2_mck.6.2.0.pack</originalPack>
    </component>
    <component apiversion="" class="CMSIS" condition="" group="Main" subgroup="CoreM" variant="" vendor="Arm" version="6.1.0+fsp.6.2.0">
      <description>Arm CMSIS Version 6 - Core (M)</description>
      <originalPack>Arm.CMSIS6.6.1.0+fsp.6.2.0.pack</originalPack>
    </component>
    <component apiversion="" class="BSP" condition="" group="ra6t2" subgroup="device" variant="R7FA6T2BD3CFP" vendor="Renesas" version="6.2.0">
      <description>Board support package for R7FA6T2BD3CFP</description>
      <originalPack>Renesas.RA_mcu_ra6t2.6.2.0.pack</originalPack>
    </component>
    <component apiversion="" class="BSP" condition="" group="ra6t2" subgroup="device" variant="" vendor="Renesas" version="6.2.0">
      <description>Board support package for RA6T2</description>
      <originalPack>Renesas.RA_mcu_ra6t2.6.2.0.pack</originalPack>
    </component>
    <component apiversion="" class="BSP" condition="" group="ra6t2" subgroup="fsp" variant="" vendor="Renesas" version="6.2.0">
      <description>Board support package for RA6T2 - FSP Data</description>
      <originalPack>Renesas.RA_mcu_ra6t2.6.2.0.pack</originalPack>
    </component>
    <component apiversion="" class="BSP" condition="" group="ra6t2" subgroup="linker" variant="" vendor="Renesas" version="6.2.0">
        <description>Board support package for RA6T2 - Linker</description>
        <originalPack>Renesas.RA_mcu_ra6t2.6.2.0.pack</originalPack>
        </component> 
    </raComponentSelection>
  <raElcConfiguration />
  <raIcuConfiguration />
  <raModuleConfiguration>
    <module id="module.driver.ioport_on_ioport.0">
      <property id="module.driver.ioport.name" value="g_ioport" />
      <property id="module.driver.ioport.elc_trigger_ioport1" value="_disabled" />
      <property id="module.driver.ioport.elc_trigger_ioport2" value="_disabled" />
      <property id="module.driver.ioport.elc_trigger_ioport3" value="_disabled" />
      <property id="module.driver.ioport.elc_trigger_ioport4" value="_disabled" />
      <property id="module.driver.ioport.elc_trigger_ioportb" value="_disabled" />
      <property id="module.driver.ioport.elc_trigger_ioportc" value="_disabled" />
      <property id="module.driver.ioport.elc_trigger_ioportd" value="_disabled" />
      <property id="module.driver.ioport.elc_trigger_ioporte" value="_disabled" />
      <property id="module.driver.ioport.pincfg" value="g_bsp_pin_cfg" />
    </module>
    <module id="module.driver.adc_on_adc_b.2092153079">
      <property id="module.driver.adc.name" value="g_adc" />
      <property id="module.driver.adc.adc_0_mode" value="module.driver.adc.adc_0_mode.continuous_scan" />
      <property id="module.driver.adc.adc_1_mode" value="module.driver.adc.adc_1_mode.single_scan" />
      <property id="module.driver.adc.adc_0_conversion_state" value="5" />
      <property id="module.driver.adc.adc_1_conversion_state" value="5" />
      <property id="module.driver.adc.adc_0_sync_operation" value="module.driver.adc.adc_0_sync_operation.disable" />
      <property id="module.driver.adc.adc_1_sync_operation" value="module.driver.adc.adc_1_sync_operation.disable" />
      <property id="module.driver.adc.sync_operation_control_period" value="100" />
      <property id="module.driver.adc.calibration_sampling_time" value="95" />
      <property id="module.driver.adc.calibration_conversion_time" value="5" />
      <property id="module.driver.adc.sample_and_hold_cal_sample_time" value="5" />
      <property id="module.driver.adc.sample_and_hold_cal_hold_time" value="5" />
      <property id="module.driver.adc.adc_clock_divider" value="module.driver.adc.adc_clock_divider.div_1" />
      <property id="module.driver.adc.adc_clock_source" value="module.driver.adc.adc_clock_source.pclkc" />
      <property id="module.driver.adc.p_callback" value="NULL" />
      <property id="module.driver.adc.limit_clip_ipl" value="board.icu.common.irq.priority12" />
      <property id="module.driver.adc.conversion_error_ipl_adc_0" value="board.icu.common.irq.priority12" />
      <property id="module.driver.adc.conversion_error_ipl_adc_1" value="board.icu.common.irq.priority12" />
      <property id="module.driver.adc.overflow_error_ipl_adc_0" value="board.icu.common.irq.priority12" />
      <property id="module.driver.adc.overflow_error_ipl_adc_1" value="board.icu.common.irq.priority12" />
      <property id="module.driver.adc.calibration_end_ipl_adc_0" value="board.icu.common.irq.priority12" />
      <property id="module.driver.adc.calibration_end_ipl_adc_1" value="board.icu.common.irq.priority12" />
      <property id="module.driver.adc.scan_end_ipl_group_0" value="board.icu.common.irq.priority12" />
      <property id="module.driver.adc.scan_end_ipl_group_1" value="board.icu.common.irq.priority12" />
      <property id="module.driver.adc.scan_end_ipl_group_2" value="board.icu.common.irq.priority12" />
      <property id="module.driver.adc.scan_end_ipl_group_3" value="board.icu.common.irq.priority12" />
      <property id="module.driver.adc.scan_end_ipl_group_4" value="board.icu.common.irq.priority12" />
      <property id="module.driver.adc.scan_end_ipl_group_5678" value="board.icu.common.irq.priority12" />
      <property id="module.driver.adc.fifo_overflow_ipl" value="board.icu.common.irq.priority12" />
      <property id="module.driver.adc.fifo_read_ipl_group_0" value="board.icu.common.irq.priority12" />
      <property id="module.driver.adc.fifo_read_ipl_group_1" value="board.icu.common.irq.priority12" />
      <property id="module.driver.adc.fifo_read_ipl_group_2" value="board.icu.common.irq.priority12" />
      <property id="module.driver.adc.fifo_read_ipl_group_3" value="board.icu.common.irq.priority12" />
      <property id="module.driver.adc.fifo_read_ipl_group_4" value="board.icu.common.irq.priority12" />
      <property id="module.driver.adc.fifo_read_ipl_group_5678" value="board.icu.common.irq.priority12" />
      <property id="module.driver.adc.sampling_table_id_0" value="95" />
      <property id="module.driver.adc.sampling_table_id_1" value="95" />
      <property id="module.driver.adc.sampling_table_id_2" value="95" />
      <property id="module.driver.adc.sampling_table_id_3" value="95" />
      <property id="module.driver.adc.sampling_table_id_4" value="95" />
      <property id="module.driver.adc.sampling_table_id_5" value="95" />
      <property id="module.driver.adc.sampling_table_id_6" value="95" />
      <property id="module.driver.adc.sampling_table_id_7" value="95" />
      <property id="module.driver.adc.sampling_table_id_8" value="95" />
      <property id="module.driver.adc.sampling_table_id_9" value="95" />
      <property id="module.driver.adc.sampling_table_id_10" value="95" />
      <property id="module.driver.adc.sampling_table_id_11" value="95" />
      <property id="module.driver.adc.sampling_table_id_12" value="95" />
      <property id="module.driver.adc.sampling_table_id_13" value="95" />
      <property id="module.driver.adc.sampling_table_id_14" value="95" />
      <property id="module.driver.adc.sampling_table_id_15" value="95" />
      <property id="module.driver.adc.sample_and_hold_enable_mask" value="" />
      <property id="module.driver.adc.sample_and_hold_sampling_time_012" value="95" />
      <property id="module.driver.adc.sample_and_hold_hold_time_012" value="5" />
      <property id="module.driver.adc.sample_and_hold_sampling_time_456" value="95" />
      <property id="module.driver.adc.sample_and_hold_hold_time_456" value="5" />
      <property id="module.driver.adc.pga_unit_0_mode" value="module.driver.adc.pga_unit_0_mode.disabled" />
      <property id="module.driver.adc.pga_unit_1_mode" value="module.driver.adc.pga_unit_1_mode.disabled" />
      <property id="module.driver.adc.pga_unit_2_mode" value="module.driver.adc.pga_unit_2_mode.disabled" />
      <property id="module.driver.adc.pga_unit_3_mode" value="module.driver.adc.pga_unit_3_mode.disabled" />
      <property id="module.driver.adc.pga_unit_0_diff_mode_gain" value="module.driver.adc.pga_unit_0_diff_mode_gain.1.500" />
      <property id="module.driver.adc.pga_unit_1_diff_mode_gain" value="module.driver.adc.pga_unit_1_diff_mode_gain.1.500" />
      <property id="module.driver.adc.pga_unit_2_diff_mode_gain" value="module.driver.adc.pga_unit_2_diff_mode_gain.1.500" />
      <property id="module.driver.adc.pga_unit_3_diff_mode_gain" value="module.driver.adc.pga_unit_3_diff_mode_gain.1.500" />
      <property id="module.driver.adc.pga_unit_0_single_ended_mode_gain" value="module.driver.adc.pga_unit_0_single_ended_mode_gain.2.500" />
      <property id="module.driver.adc.pga_unit_1_single_ended_mode_gain" value="module.driver.adc.pga_unit_1_single_ended_mode_gain.2.500" />
      <property id="module.driver.adc.pga_unit_2_single_ended_mode_gain" value="module.driver.adc.pga_unit_2_single_ended_mode_gain.2.500" />
      <property id="module.driver.adc.pga_unit_3_single_ended_mode_gain" value="module.driver.adc.pga_unit_3_single_ended_mode_gain.2.500" />
      <property id="module.driver.adc.user_offset_id_0" value="0" />
      <property id="module.driver.adc.user_offset_id_1" value="0" />
      <property id="module.driver.adc.user_offset_id_2" value="0" />
      <property id="module.driver.adc.user_offset_id_3" value="0" />
      <property id="module.driver.adc.user_offset_id_4" value="0" />
      <property id="module.driver.adc.user_offset_id_5" value="0" />
      <property id="module.driver.adc.user_offset_id_6" value="0" />
      <property id="module.driver.adc.user_offset_id_7" value="0" />
      <property id="module.driver.adc.user_gain_0" value="0" />
      <property id="module.driver.adc.user_gain_1" value="0" />
      <property id="module.driver.adc.user_gain_2" value="0" />
      <property id="module.driver.adc.user_gain_3" value="0" />
      <property id="module.driver.adc.user_gain_4" value="0" />
      <property id="module.driver.adc.user_gain_5" value="0" />
      <property id="module.driver.adc.user_gain_6" value="0" />
      <property id="module.driver.adc.user_gain_7" value="0" />
      <property id="module.driver.adc.limiter_clip_interrupt_enable_mask" value="" />
      <property id="module.driver.adc.limiter_clip_lower_0" value="0" />
      <property id="module.driver.adc.limiter_clip_upper_0" value="0" />
      <property id="module.driver.adc.limiter_clip_lower_1" value="0" />
      <property id="module.driver.adc.limiter_clip_upper_1" value="0" />
      <property id="module.driver.adc.limiter_clip_lower_2" value="0" />
      <property id="module.driver.adc.limiter_clip_upper_2" value="0" />
      <property id="module.driver.adc.limiter_clip_lower_3" value="0" />
      <property id="module.driver.adc.limiter_clip_upper_3" value="0" />
      <property id="module.driver.adc.limiter_clip_lower_4" value="0" />
      <property id="module.driver.adc.limiter_clip_upper_4" value="0" />
      <property id="module.driver.adc.limiter_clip_lower_5" value="0" />
      <property id="module.driver.adc.limiter_clip_upper_5" value="0" />
      <property id="module.driver.adc.limiter_clip_lower_6" value="0" />
      <property id="module.driver.adc.limiter_clip_upper_6" value="0" />
      <property id="module.driver.adc.limiter_clip_lower_7" value="0" />
      <property id="module.driver.adc.limiter_clip_upper_7" value="0" />
      <property id="module.driver.adc.virtual_channel_0_scan_group" value="module.driver.adc.virtual_channel_0_scan_group.scan_group_0" />
      <property id="module.driver.adc.virtual_channel_0_channel_select" value="module.driver.adc.virtual_channel_0_channel_select.temperature_sensor" />
      <property id="module.driver.adc.virtual_channel_0_sampling_table_id" value="module.driver.adc.virtual_channel_0_sampling_table_id.sampling_state_entry_0" />
      <property id="module.driver.adc.virtual_channel_0_gain_table" value="module.driver.adc.virtual_channel_0_gain_table.disabled" />
      <property id="module.driver.adc.virtual_channel_0_offset_table" value="module.driver.adc.virtual_channel_0_offset_table.disabled" />
      <property id="module.driver.adc.virtual_channel_0_add_average_mode" value="module.driver.adc.virtual_channel_0_add_average_mode.disabled" />
      <property id="module.driver.adc.virtual_channel_0_add_average_count" value="module.driver.adc.virtual_channel_0_add_average_count.1_time_conversion" />
      <property id="module.driver.adc.virtual_channel_0_limit_clip_table_id" value="module.driver.adc.virtual_channel_0_limit_clip_table_id.disabled" />
      <property id="module.driver.adc.virtual_channel_0_resolution_format" value="module.driver.adc.virtual_channel_0_resolution_format.12_bit_data_format" />
      <property id="module.driver.adc.virtual_channel_1_scan_group" value="module.driver.adc.virtual_channel_1_scan_group.none" />
      <property id="module.driver.adc.virtual_channel_1_channel_select" value="module.driver.adc.virtual_channel_1_channel_select.an000" />
      <property id="module.driver.adc.virtual_channel_1_sampling_table_id" value="module.driver.adc.virtual_channel_1_sampling_table_id.sampling_state_entry_0" />
      <property id="module.driver.adc.virtual_channel_1_gain_table" value="module.driver.adc.virtual_channel_1_gain_table.disabled" />
      <property id="module.driver.adc.virtual_channel_1_offset_table" value="module.driver.adc.virtual_channel_1_offset_table.disabled" />
      <property id="module.driver.adc.virtual_channel_1_add_average_mode" value="module.driver.adc.virtual_channel_1_add_average_mode.disabled" />
      <property id="module.driver.adc.virtual_channel_1_add_average_count" value="module.driver.adc.virtual_channel_1_add_average_count.1_time_conversion" />
      <property id="module.driver.adc.virtual_channel_1_limit_clip_table_id" value="module.driver.adc.virtual_channel_1_limit_clip_table_id.disabled" />
      <property id="module.driver.adc.virtual_channel_1_resolution_format" value="module.driver.adc.virtual_channel_1_resolution_format.12_bit_data_format" />
      <property id="module.driver.adc.virtual_channel_2_scan_group" value="module.driver.adc.virtual_channel_2_scan_group.none" />
      <property id="module.driver.adc.virtual_channel_2_channel_select" value="module.driver.adc.virtual_channel_2_channel_select.an000" />
      <property id="module.driver.adc.virtual_channel_2_sampling_table_id" value="module.driver.adc.virtual_channel_2_sampling_table_id.sampling_state_entry_0" />
      <property id="module.driver.adc.virtual_channel_2_gain_table" value="module.driver.adc.virtual_channel_2_gain_table.disabled" />
      <property id="module.driver.adc.virtual_channel_2_offset_table" value="module.driver.adc.virtual_channel_2_offset_table.disabled" />
      <property id="module.driver.adc.virtual_channel_2_add_average_mode" value="module.driver.adc.virtual_channel_2_add_average_mode.disabled" />
      <property id="module.driver.adc.virtual_channel_2_add_average_count" value="module.driver.adc.virtual_channel_2_add_average_count.1_time_conversion" />
      <property id="module.driver.adc.virtual_channel_2_limit_clip_table_id" value="module.driver.adc.virtual_channel_2_limit_clip_table_id.disabled" />
      <property id="module.driver.adc.virtual_channel_2_resolution_format" value="module.driver.adc.virtual_channel_2_resolution_format.12_bit_data_format" />
      <property id="module.driver.adc.virtual_channel_3_scan_group" value="module.driver.adc.virtual_channel_3_scan_group.none" />
      <property id="module.driver.adc.virtual_channel_3_channel_select" value="module.driver.adc.virtual_channel_3_channel_select.an000" />
      <property id="module.driver.adc.virtual_channel_3_sampling_table_id" value="module.driver.adc.virtual_channel_3_sampling_table_id.sampling_state_entry_0" />
      <property id="module.driver.adc.virtual_channel_3_gain_table" value="module.driver.adc.virtual_channel_3_gain_table.disabled" />
      <property id="module.driver.adc.virtual_channel_3_offset_table" value="module.driver.adc.virtual_channel_3_offset_table.disabled" />
      <property id="module.driver.adc.virtual_channel_3_add_average_mode" value="module.driver.adc.virtual_channel_3_add_average_mode.disabled" />
      <property id="module.driver.adc.virtual_channel_3_add_average_count" value="module.driver.adc.virtual_channel_3_add_average_count.1_time_conversion" />
      <property id="module.driver.adc.virtual_channel_3_limit_clip_table_id" value="module.driver.adc.virtual_channel_3_limit_clip_table_id.disabled" />
      <property id="module.driver.adc.virtual_channel_3_resolution_format" value="module.driver.adc.virtual_channel_3_resolution_format.12_bit_data_format" />
      <property id="module.driver.adc.virtual_channel_4_scan_group" value="module.driver.adc.virtual_channel_4_scan_group.none" />
      <property id="module.driver.adc.virtual_channel_4_channel_select" value="module.driver.adc.virtual_channel_4_channel_select.an000" />
      <property id="module.driver.adc.virtual_channel_4_sampling_table_id" value="module.driver.adc.virtual_channel_4_sampling_table_id.sampling_state_entry_0" />
      <property id="module.driver.adc.virtual_channel_4_gain_table" value="module.driver.adc.virtual_channel_4_gain_table.disabled" />
      <property id="module.driver.adc.virtual_channel_4_offset_table" value="module.driver.adc.virtual_channel_4_offset_table.disabled" />
      <property id="module.driver.adc.virtual_channel_4_add_average_mode" value="module.driver.adc.virtual_channel_4_add_average_mode.disabled" />
      <property id="module.driver.adc.virtual_channel_4_add_average_count" value="module.driver.adc.virtual_channel_4_add_average_count.1_time_conversion" />
      <property id="module.driver.adc.virtual_channel_4_limit_clip_table_id" value="module.driver.adc.virtual_channel_4_limit_clip_table_id.disabled" />
      <property id="module.driver.adc.virtual_channel_4_resolution_format" value="module.driver.adc.virtual_channel_4_resolution_format.12_bit_data_format" />
      <property id="module.driver.adc.virtual_channel_5_scan_group" value="module.driver.adc.virtual_channel_5_scan_group.none" />
      <property id="module.driver.adc.virtual_channel_5_channel_select" value="module.driver.adc.virtual_channel_5_channel_select.an000" />
      <property id="module.driver.adc.virtual_channel_5_sampling_table_id" value="module.driver.adc.virtual_channel_5_sampling_table_id.sampling_state_entry_0" />
      <property id="module.driver.adc.virtual_channel_5_gain_table" value="module.driver.adc.virtual_channel_5_gain_table.disabled" />
      <property id="module.driver.adc.virtual_channel_5_offset_table" value="module.driver.adc.virtual_channel_5_offset_table.disabled" />
      <property id="module.driver.adc.virtual_channel_5_add_average_mode" value="module.driver.adc.virtual_channel_5_add_average_mode.disabled" />
      <property id="module.driver.adc.virtual_channel_5_add_average_count" value="module.driver.adc.virtual_channel_5_add_average_count.1_time_conversion" />
      <property id="module.driver.adc.virtual_channel_5_limit_clip_table_id" value="module.driver.adc.virtual_channel_5_limit_clip_table_id.disabled" />
      <property id="module.driver.adc.virtual_channel_5_resolution_format" value="module.driver.adc.virtual_channel_5_resolution_format.12_bit_data_format" />
      <property id="module.driver.adc.virtual_channel_6_scan_group" value="module.driver.adc.virtual_channel_6_scan_group.none" />
      <property id="module.driver.adc.virtual_channel_6_channel_select" value="module.driver.adc.virtual_channel_6_channel_select.an000" />
      <property id="module.driver.adc.virtual_channel_6_sampling_table_id" value="module.driver.adc.virtual_channel_6_sampling_table_id.sampling_state_entry_0" />
      <property id="module.driver.adc.virtual_channel_6_gain_table" value="module.driver.adc.virtual_channel_6_gain_table.disabled" />
      <property id="module.driver.adc.virtual_channel_6_offset_table" value="module.driver.adc.virtual_channel_6_offset_table.disabled" />
      <property id="module.driver.adc.virtual_channel_6_add_average_mode" value="module.driver.adc.virtual_channel_6_add_average_mode.disabled" />
      <property id="module.driver.adc.virtual_channel_6_add_average_count" value="module.driver.adc.virtual_channel_6_add_average_count.1_time_conversion" />
      <property id="module.driver.adc.virtual_channel_6_limit_clip_table_id" value="module.driver.adc.virtual_channel_6_limit_clip_table_id.disabled" />
      <property id="module.driver.adc.virtual_channel_6_resolution_format" value="module.driver.adc.virtual_channel_6_resolution_format.12_bit_data_format" />
      <property id="module.driver.adc.virtual_channel_7_scan_group" value="module.driver.adc.virtual_channel_7_scan_group.none" />
      <property id="module.driver.adc.virtual_channel_7_channel_select" value="module.driver.adc.virtual_channel_7_channel_select.an000" />
      <property id="module.driver.adc.virtual_channel_7_sampling_table_id" value="module.driver.adc.virtual_channel_7_sampling_table_id.sampling_state_entry_0" />
      <property id="module.driver.adc.virtual_channel_7_gain_table" value="module.driver.adc.virtual_channel_7_gain_table.disabled" />
      <property id="module.driver.adc.virtual_channel_7_offset_table" value="module.driver.adc.virtual_channel_7_offset_table.disabled" />
      <property id="module.driver.adc.virtual_channel_7_add_average_mode" value="module.driver.adc.virtual_channel_7_add_average_mode.disabled" />
      <property id="module.driver.adc.virtual_channel_7_add_average_count" value="module.driver.adc.virtual_channel_7_add_average_count.1_time_conversion" />
      <property id="module.driver.adc.virtual_channel_7_limit_clip_table_id" value="module.driver.adc.virtual_channel_7_limit_clip_table_id.disabled" />
      <property id="module.driver.adc.virtual_channel_7_resolution_format" value="module.driver.adc.virtual_channel_7_resolution_format.12_bit_data_format" />
      <property id="module.driver.adc.virtual_channel_8_scan_group" value="module.driver.adc.virtual_channel_8_scan_group.none" />
      <property id="module.driver.adc.virtual_channel_8_channel_select" value="module.driver.adc.virtual_channel_8_channel_select.an000" />
      <property id="module.driver.adc.virtual_channel_8_sampling_table_id" value="module.driver.adc.virtual_channel_8_sampling_table_id.sampling_state_entry_0" />
      <property id="module.driver.adc.virtual_channel_8_gain_table" value="module.driver.adc.virtual_channel_8_gain_table.disabled" />
      <property id="module.driver.adc.virtual_channel_8_offset_table" value="module.driver.adc.virtual_channel_8_offset_table.disabled" />
      <property id="module.driver.adc.virtual_channel_8_add_average_mode" value="module.driver.adc.virtual_channel_8_add_average_mode.disabled" />
      <property id="module.driver.adc.virtual_channel_8_add_average_count" value="module.driver.adc.virtual_channel_8_add_average_count.1_time_conversion" />
      <property id="module.driver.adc.virtual_channel_8_limit_clip_table_id" value="module.driver.adc.virtual_channel_8_limit_clip_table_id.disabled" />
      <property id="module.driver.adc.virtual_channel_8_resolution_format" value="module.driver.adc.virtual_channel_8_resolution_format.12_bit_data_format" />
      <property id="module.driver.adc.virtual_channel_9_scan_group" value="module.driver.adc.virtual_channel_9_scan_group.none" />
      <property id="module.driver.adc.virtual_channel_9_channel_select" value="module.driver.adc.virtual_channel_9_channel_select.an000" />
      <property id="module.driver.adc.virtual_channel_9_sampling_table_id" value="module.driver.adc.virtual_channel_9_sampling_table_id.sampling_state_entry_0" />
      <property id="module.driver.adc.virtual_channel_9_gain_table" value="module.driver.adc.virtual_channel_9_gain_table.disabled" />
      <property id="module.driver.adc.virtual_channel_9_offset_table" value="module.driver.adc.virtual_channel_9_offset_table.disabled" />
      <property id="module.driver.adc.virtual_channel_9_add_average_mode" value="module.driver.adc.virtual_channel_9_add_average_mode.disabled" />
      <property id="module.driver.adc.virtual_channel_9_add_average_count" value="module.driver.adc.virtual_channel_9_add_average_count.1_time_conversion" />
      <property id="module.driver.adc.virtual_channel_9_limit_clip_table_id" value="module.driver.adc.virtual_channel_9_limit_clip_table_id.disabled" />
      <property id="module.driver.adc.virtual_channel_9_resolution_format" value="module.driver.adc.virtual_channel_9_resolution_format.12_bit_data_format" />
      <property id="module.driver.adc.virtual_channel_10_scan_group" value="module.driver.adc.virtual_channel_10_scan_group.none" />
      <property id="module.driver.adc.virtual_channel_10_channel_select" value="module.driver.adc.virtual_channel_10_channel_select.an000" />
      <property id="module.driver.adc.virtual_channel_10_sampling_table_id" value="module.driver.adc.virtual_channel_10_sampling_table_id.sampling_state_entry_0" />
      <property id="module.driver.adc.virtual_channel_10_gain_table" value="module.driver.adc.virtual_channel_10_gain_table.disabled" />
      <property id="module.driver.adc.virtual_channel_10_offset_table" value="module.driver.adc.virtual_channel_10_offset_table.disabled" />
      <property id="module.driver.adc.virtual_channel_10_add_average_mode" value="module.driver.adc.virtual_channel_10_add_average_mode.disabled" />
      <property id="module.driver.adc.virtual_channel_10_add_average_count" value="module.driver.adc.virtual_channel_10_add_average_count.1_time_conversion" />
      <property id="module.driver.adc.virtual_channel_10_limit_clip_table_id" value="module.driver.adc.virtual_channel_10_limit_clip_table_id.disabled" />
      <property id="module.driver.adc.virtual_channel_10_resolution_format" value="module.driver.adc.virtual_channel_10_resolution_format.12_bit_data_format" />
      <property id="module.driver.adc.virtual_channel_11_scan_group" value="module.driver.adc.virtual_channel_11_scan_group.none" />
      <property id="module.driver.adc.virtual_channel_11_channel_select" value="module.driver.adc.virtual_channel_11_channel_select.an000" />
      <property id="module.driver.adc.virtual_channel_11_sampling_table_id" value="module.driver.adc.virtual_channel_11_sampling_table_id.sampling_state_entry_0" />
      <property id="module.driver.adc.virtual_channel_11_gain_table" value="module.driver.adc.virtual_channel_11_gain_table.disabled" />
      <property id="module.driver.adc.virtual_channel_11_offset_table" value="module.driver.adc.virtual_channel_11_offset_table.disabled" />
      <property id="module.driver.adc.virtual_channel_11_add_average_mode" value="module.driver.adc.virtual_channel_11_add_average_mode.disabled" />
      <property id="module.driver.adc.virtual_channel_11_add_average_count" value="module.driver.adc.virtual_channel_11_add_average_count.1_time_conversion" />
      <property id="module.driver.adc.virtual_channel_11_limit_clip_table_id" value="module.driver.adc.virtual_channel_11_limit_clip_table_id.disabled" />
      <property id="module.driver.adc.virtual_channel_11_resolution_format" value="module.driver.adc.virtual_channel_11_resolution_format.12_bit_data_format" />
      <property id="module.driver.adc.virtual_channel_12_scan_group" value="module.driver.adc.virtual_channel_12_scan_group.none" />
      <property id="module.driver.adc.virtual_channel_12_channel_select" value="module.driver.adc.virtual_channel_12_channel_select.an000" />
      <property id="module.driver.adc.virtual_channel_12_sampling_table_id" value="module.driver.adc.virtual_channel_12_sampling_table_id.sampling_state_entry_0" />
      <property id="module.driver.adc.virtual_channel_12_gain_table" value="module.driver.adc.virtual_channel_12_gain_table.disabled" />
      <property id="module.driver.adc.virtual_channel_12_offset_table" value="module.driver.adc.virtual_channel_12_offset_table.disabled" />
      <property id="module.driver.adc.virtual_channel_12_add_average_mode" value="module.driver.adc.virtual_channel_12_add_average_mode.disabled" />
      <property id="module.driver.adc.virtual_channel_12_add_average_count" value="module.driver.adc.virtual_channel_12_add_average_count.1_time_conversion" />
      <property id="module.driver.adc.virtual_channel_12_limit_clip_table_id" value="module.driver.adc.virtual_channel_12_limit_clip_table_id.disabled" />
      <property id="module.driver.adc.virtual_channel_12_resolution_format" value="module.driver.adc.virtual_channel_12_resolution_format.12_bit_data_format" />
      <property id="module.driver.adc.virtual_channel_13_scan_group" value="module.driver.adc.virtual_channel_13_scan_group.none" />
      <property id="module.driver.adc.virtual_channel_13_channel_select" value="module.driver.adc.virtual_channel_13_channel_select.an000" />
      <property id="module.driver.adc.virtual_channel_13_sampling_table_id" value="module.driver.adc.virtual_channel_13_sampling_table_id.sampling_state_entry_0" />
      <property id="module.driver.adc.virtual_channel_13_gain_table" value="module.driver.adc.virtual_channel_13_gain_table.disabled" />
      <property id="module.driver.adc.virtual_channel_13_offset_table" value="module.driver.adc.virtual_channel_13_offset_table.disabled" />
      <property id="module.driver.adc.virtual_channel_13_add_average_mode" value="module.driver.adc.virtual_channel_13_add_average_mode.disabled" />
      <property id="module.driver.adc.virtual_channel_13_add_average_count" value="module.driver.adc.virtual_channel_13_add_average_count.1_time_conversion" />
      <property id="module.driver.adc.virtual_channel_13_limit_clip_table_id" value="module.driver.adc.virtual_channel_13_limit_clip_table_id.disabled" />
      <property id="module.driver.adc.virtual_channel_13_resolution_format" value="module.driver.adc.virtual_channel_13_resolution_format.12_bit_data_format" />
      <property id="module.driver.adc.virtual_channel_14_scan_group" value="module.driver.adc.virtual_channel_14_scan_group.none" />
      <property id="module.driver.adc.virtual_channel_14_channel_select" value="module.driver.adc.virtual_channel_14_channel_select.an000" />
      <property id="module.driver.adc.virtual_channel_14_sampling_table_id" value="module.driver.adc.virtual_channel_14_sampling_table_id.sampling_state_entry_0" />
      <property id="module.driver.adc.virtual_channel_14_gain_table" value="module.driver.adc.virtual_channel_14_gain_table.disabled" />
      <property id="module.driver.adc.virtual_channel_14_offset_table" value="module.driver.adc.virtual_channel_14_offset_table.disabled" />
      <property id="module.driver.adc.virtual_channel_14_add_average_mode" value="module.driver.adc.virtual_channel_14_add_average_mode.disabled" />
      <property id="module.driver.adc.virtual_channel_14_add_average_count" value="module.driver.adc.virtual_channel_14_add_average_count.1_time_conversion" />
      <property id="module.driver.adc.virtual_channel_14_limit_clip_table_id" value="module.driver.adc.virtual_channel_14_limit_clip_table_id.disabled" />
      <property id="module.driver.adc.virtual_channel_14_resolution_format" value="module.driver.adc.virtual_channel_14_resolution_format.12_bit_data_format" />
      <property id="module.driver.adc.virtual_channel_15_scan_group" value="module.driver.adc.virtual_channel_15_scan_group.none" />
      <property id="module.driver.adc.virtual_channel_15_channel_select" value="module.driver.adc.virtual_channel_15_channel_select.an000" />
      <property id="module.driver.adc.virtual_channel_15_sampling_table_id" value="module.driver.adc.virtual_channel_15_sampling_table_id.sampling_state_entry_0" />
      <property id="module.driver.adc.virtual_channel_15_gain_table" value="module.driver.adc.virtual_channel_15_gain_table.disabled" />
      <property id="module.driver.adc.virtual_channel_15_offset_table" value="module.driver.adc.virtual_channel_15_offset_table.disabled" />
      <property id="module.driver.adc.virtual_channel_15_add_average_mode" value="module.driver.adc.virtual_channel_15_add_average_mode.disabled" />
      <property id="module.driver.adc.virtual_channel_15_add_average_count" value="module.driver.adc.virtual_channel_15_add_average_count.1_time_conversion" />
      <property id="module.driver.adc.virtual_channel_15_limit_clip_table_id" value="module.driver.adc.virtual_channel_15_limit_clip_table_id.disabled" />
      <property id="module.driver.adc.virtual_channel_15_resolution_format" value="module.driver.adc.virtual_channel_15_resolution_format.12_bit_data_format" />
      <property id="module.driver.adc.virtual_channel_16_scan_group" value="module.driver.adc.virtual_channel_16_scan_group.none" />
      <property id="module.driver.adc.virtual_channel_16_channel_select" value="module.driver.adc.virtual_channel_16_channel_select.an000" />
      <property id="module.driver.adc.virtual_channel_16_sampling_table_id" value="module.driver.adc.virtual_channel_16_sampling_table_id.sampling_state_entry_0" />
      <property id="module.driver.adc.virtual_channel_16_gain_table" value="module.driver.adc.virtual_channel_16_gain_table.disabled" />
      <property id="module.driver.adc.virtual_channel_16_offset_table" value="module.driver.adc.virtual_channel_16_offset_table.disabled" />
      <property id="module.driver.adc.virtual_channel_16_add_average_mode" value="module.driver.adc.virtual_channel_16_add_average_mode.disabled" />
      <property id="module.driver.adc.virtual_channel_16_add_average_count" value="module.driver.adc.virtual_channel_16_add_average_count.1_time_conversion" />
      <property id="module.driver.adc.virtual_channel_16_limit_clip_table_id" value="module.driver.adc.virtual_channel_16_limit_clip_table_id.disabled" />
      <property id="module.driver.adc.virtual_channel_16_resolution_format" value="module.driver.adc.virtual_channel_16_resolution_format.12_bit_data_format" />
      <property id="module.driver.adc.virtual_channel_17_scan_group" value="module.driver.adc.virtual_channel_17_scan_group.none" />
      <property id="module.driver.adc.virtual_channel_17_channel_select" value="module.driver.adc.virtual_channel_17_channel_select.an000" />
      <property id="module.driver.adc.virtual_channel_17_sampling_table_id" value="module.driver.adc.virtual_channel_17_sampling_table_id.sampling_state_entry_0" />
      <property id="module.driver.adc.virtual_channel_17_gain_table" value="module.driver.adc.virtual_channel_17_gain_table.disabled" />
      <property id="module.driver.adc.virtual_channel_17_offset_table" value="module.driver.adc.virtual_channel_17_offset_table.disabled" />
      <property id="module.driver.adc.virtual_channel_17_add_average_mode" value="module.driver.adc.virtual_channel_17_add_average_mode.disabled" />
      <property id="module.driver.adc.virtual_channel_17_add_average_count" value="module.driver.adc.virtual_channel_17_add_average_count.1_time_conversion" />
      <property id="module.driver.adc.virtual_channel_17_limit_clip_table_id" value="module.driver.adc.virtual_channel_17_limit_clip_table_id.disabled" />
      <property id="module.driver.adc.virtual_channel_17_resolution_format" value="module.driver.adc.virtual_channel_17_resolution_format.12_bit_data_format" />
      <property id="module.driver.adc.virtual_channel_18_scan_group" value="module.driver.adc.virtual_channel_18_scan_group.none" />
      <property id="module.driver.adc.virtual_channel_18_channel_select" value="module.driver.adc.virtual_channel_18_channel_select.an000" />
      <property id="module.driver.adc.virtual_channel_18_sampling_table_id" value="module.driver.adc.virtual_channel_18_sampling_table_id.sampling_state_entry_0" />
      <property id="module.driver.adc.virtual_channel_18_gain_table" value="module.driver.adc.virtual_channel_18_gain_table.disabled" />
      <property id="module.driver.adc.virtual_channel_18_offset_table" value="module.driver.adc.virtual_channel_18_offset_table.disabled" />
      <property id="module.driver.adc.virtual_channel_18_add_average_mode" value="module.driver.adc.virtual_channel_18_add_average_mode.disabled" />
      <property id="module.driver.adc.virtual_channel_18_add_average_count" value="module.driver.adc.virtual_channel_18_add_average_count.1_time_conversion" />
      <property id="module.driver.adc.virtual_channel_18_limit_clip_table_id" value="module.driver.adc.virtual_channel_18_limit_clip_table_id.disabled" />
      <property id="module.driver.adc.virtual_channel_18_resolution_format" value="module.driver.adc.virtual_channel_18_resolution_format.12_bit_data_format" />
      <property id="module.driver.adc.virtual_channel_19_scan_group" value="module.driver.adc.virtual_channel_19_scan_group.none" />
      <property id="module.driver.adc.virtual_channel_19_channel_select" value="module.driver.adc.virtual_channel_19_channel_select.an000" />
      <property id="module.driver.adc.virtual_channel_19_sampling_table_id" value="module.driver.adc.virtual_channel_19_sampling_table_id.sampling_state_entry_0" />
      <property id="module.driver.adc.virtual_channel_19_gain_table" value="module.driver.adc.virtual_channel_19_gain_table.disabled" />
      <property id="module.driver.adc.virtual_channel_19_offset_table" value="module.driver.adc.virtual_channel_19_offset_table.disabled" />
      <property id="module.driver.adc.virtual_channel_19_add_average_mode" value="module.driver.adc.virtual_channel_19_add_average_mode.disabled" />
      <property id="module.driver.adc.virtual_channel_19_add_average_count" value="module.driver.adc.virtual_channel_19_add_average_count.1_time_conversion" />
      <property id="module.driver.adc.virtual_channel_19_limit_clip_table_id" value="module.driver.adc.virtual_channel_19_limit_clip_table_id.disabled" />
      <property id="module.driver.adc.virtual_channel_19_resolution_format" value="module.driver.adc.virtual_channel_19_resolution_format.12_bit_data_format" />
      <property id="module.driver.adc.virtual_channel_20_scan_group" value="module.driver.adc.virtual_channel_20_scan_group.none" />
      <property id="module.driver.adc.virtual_channel_20_channel_select" value="module.driver.adc.virtual_channel_20_channel_select.an000" />
      <property id="module.driver.adc.virtual_channel_20_sampling_table_id" value="module.driver.adc.virtual_channel_20_sampling_table_id.sampling_state_entry_0" />
      <property id="module.driver.adc.virtual_channel_20_gain_table" value="module.driver.adc.virtual_channel_20_gain_table.disabled" />
      <property id="module.driver.adc.virtual_channel_20_offset_table" value="module.driver.adc.virtual_channel_20_offset_table.disabled" />
      <property id="module.driver.adc.virtual_channel_20_add_average_mode" value="module.driver.adc.virtual_channel_20_add_average_mode.disabled" />
      <property id="module.driver.adc.virtual_channel_20_add_average_count" value="module.driver.adc.virtual_channel_20_add_average_count.1_time_conversion" />
      <property id="module.driver.adc.virtual_channel_20_limit_clip_table_id" value="module.driver.adc.virtual_channel_20_limit_clip_table_id.disabled" />
      <property id="module.driver.adc.virtual_channel_20_resolution_format" value="module.driver.adc.virtual_channel_20_resolution_format.12_bit_data_format" />
      <property id="module.driver.adc.virtual_channel_21_scan_group" value="module.driver.adc.virtual_channel_21_scan_group.none" />
      <property id="module.driver.adc.virtual_channel_21_channel_select" value="module.driver.adc.virtual_channel_21_channel_select.an000" />
      <property id="module.driver.adc.virtual_channel_21_sampling_table_id" value="module.driver.adc.virtual_channel_21_sampling_table_id.sampling_state_entry_0" />
      <property id="module.driver.adc.virtual_channel_21_gain_table" value="module.driver.adc.virtual_channel_21_gain_table.disabled" />
      <property id="module.driver.adc.virtual_channel_21_offset_table" value="module.driver.adc.virtual_channel_21_offset_table.disabled" />
      <property id="module.driver.adc.virtual_channel_21_add_average_mode" value="module.driver.adc.virtual_channel_21_add_average_mode.disabled" />
      <property id="module.driver.adc.virtual_channel_21_add_average_count" value="module.driver.adc.virtual_channel_21_add_average_count.1_time_conversion" />
      <property id="module.driver.adc.virtual_channel_21_limit_clip_table_id" value="module.driver.adc.virtual_channel_21_limit_clip_table_id.disabled" />
      <property id="module.driver.adc.virtual_channel_21_resolution_format" value="module.driver.adc.virtual_channel_21_resolution_format.12_bit_data_format" />
      <property id="module.driver.adc.virtual_channel_22_scan_group" value="module.driver.adc.virtual_channel_22_scan_group.none" />
      <property id="module.driver.adc.virtual_channel_22_channel_select" value="module.driver.adc.virtual_channel_22_channel_select.an000" />
      <property id="module.driver.adc.virtual_channel_22_sampling_table_id" value="module.driver.adc.virtual_channel_22_sampling_table_id.sampling_state_entry_0" />
      <property id="module.driver.adc.virtual_channel_22_gain_table" value="module.driver.adc.virtual_channel_22_gain_table.disabled" />
      <property id="module.driver.adc.virtual_channel_22_offset_table" value="module.driver.adc.virtual_channel_22_offset_table.disabled" />
      <property id="module.driver.adc.virtual_channel_22_add_average_mode" value="module.driver.adc.virtual_channel_22_add_average_mode.disabled" />
      <property id="module.driver.adc.virtual_channel_22_add_average_count" value="module.driver.adc.virtual_channel_22_add_average_count.1_time_conversion" />
      <property id="module.driver.adc.virtual_channel_22_limit_clip_table_id" value="module.driver.adc.virtual_channel_22_limit_clip_table_id.disabled" />
      <property id="module.driver.adc.virtual_channel_22_resolution_format" value="module.driver.adc.virtual_channel_22_resolution_format.12_bit_data_format" />
      <property id="module.driver.adc.virtual_channel_23_scan_group" value="module.driver.adc.virtual_channel_23_scan_group.none" />
      <property id="module.driver.adc.virtual_channel_23_channel_select" value="module.driver.adc.virtual_channel_23_channel_select.an000" />
      <property id="module.driver.adc.virtual_channel_23_sampling_table_id" value="module.driver.adc.virtual_channel_23_sampling_table_id.sampling_state_entry_0" />
      <property id="module.driver.adc.virtual_channel_23_gain_table" value="module.driver.adc.virtual_channel_23_gain_table.disabled" />
      <property id="module.driver.adc.virtual_channel_23_offset_table" value="module.driver.adc.virtual_channel_23_offset_table.disabled" />
      <property id="module.driver.adc.virtual_channel_23_add_average_mode" value="module.driver.adc.virtual_channel_23_add_average_mode.disabled" />
      <property id="module.driver.adc.virtual_channel_23_add_average_count" value="module.driver.adc.virtual_channel_23_add_average_count.1_time_conversion" />
      <property id="module.driver.adc.virtual_channel_23_limit_clip_table_id" value="module.driver.adc.virtual_channel_23_limit_clip_table_id.disabled" />
      <property id="module.driver.adc.virtual_channel_23_resolution_format" value="module.driver.adc.virtual_channel_23_resolution_format.12_bit_data_format" />
      <property id="module.driver.adc.virtual_channel_24_scan_group" value="module.driver.adc.virtual_channel_24_scan_group.none" />
      <property id="module.driver.adc.virtual_channel_24_channel_select" value="module.driver.adc.virtual_channel_24_channel_select.an000" />
      <property id="module.driver.adc.virtual_channel_24_sampling_table_id" value="module.driver.adc.virtual_channel_24_sampling_table_id.sampling_state_entry_0" />
      <property id="module.driver.adc.virtual_channel_24_gain_table" value="module.driver.adc.virtual_channel_24_gain_table.disabled" />
      <property id="module.driver.adc.virtual_channel_24_offset_table" value="module.driver.adc.virtual_channel_24_offset_table.disabled" />
      <property id="module.driver.adc.virtual_channel_24_add_average_mode" value="module.driver.adc.virtual_channel_24_add_average_mode.disabled" />
      <property id="module.driver.adc.virtual_channel_24_add_average_count" value="module.driver.adc.virtual_channel_24_add_average_count.1_time_conversion" />
      <property id="module.driver.adc.virtual_channel_24_limit_clip_table_id" value="module.driver.adc.virtual_channel_24_limit_clip_table_id.disabled" />
      <property id="module.driver.adc.virtual_channel_24_resolution_format" value="module.driver.adc.virtual_channel_24_resolution_format.12_bit_data_format" />
      <property id="module.driver.adc.virtual_channel_25_scan_group" value="module.driver.adc.virtual_channel_25_scan_group.none" />
      <property id="module.driver.adc.virtual_channel_25_channel_select" value="module.driver.adc.virtual_channel_25_channel_select.an000" />
      <property id="module.driver.adc.virtual_channel_25_sampling_table_id" value="module.driver.adc.virtual_channel_25_sampling_table_id.sampling_state_entry_0" />
      <property id="module.driver.adc.virtual_channel_25_gain_table" value="module.driver.adc.virtual_channel_25_gain_table.disabled" />
      <property id="module.driver.adc.virtual_channel_25_offset_table" value="module.driver.adc.virtual_channel_25_offset_table.disabled" />
      <property id="module.driver.adc.virtual_channel_25_add_average_mode" value="module.driver.adc.virtual_channel_25_add_average_mode.disabled" />
      <property id="module.driver.adc.virtual_channel_25_add_average_count" value="module.driver.adc.virtual_channel_25_add_average_count.1_time_conversion" />
      <property id="module.driver.adc.virtual_channel_25_limit_clip_table_id" value="module.driver.adc.virtual_channel_25_limit_clip_table_id.disabled" />
      <property id="module.driver.adc.virtual_channel_25_resolution_format" value="module.driver.adc.virtual_channel_25_resolution_format.12_bit_data_format" />
      <property id="module.driver.adc.virtual_channel_26_scan_group" value="module.driver.adc.virtual_channel_26_scan_group.none" />
      <property id="module.driver.adc.virtual_channel_26_channel_select" value="module.driver.adc.virtual_channel_26_channel_select.an000" />
      <property id="module.driver.adc.virtual_channel_26_sampling_table_id" value="module.driver.adc.virtual_channel_26_sampling_table_id.sampling_state_entry_0" />
      <property id="module.driver.adc.virtual_channel_26_gain_table" value="module.driver.adc.virtual_channel_26_gain_table.disabled" />
      <property id="module.driver.adc.virtual_channel_26_offset_table" value="module.driver.adc.virtual_channel_26_offset_table.disabled" />
      <property id="module.driver.adc.virtual_channel_26_add_average_mode" value="module.driver.adc.virtual_channel_26_add_average_mode.disabled" />
      <property id="module.driver.adc.virtual_channel_26_add_average_count" value="module.driver.adc.virtual_channel_26_add_average_count.1_time_conversion" />
      <property id="module.driver.adc.virtual_channel_26_limit_clip_table_id" value="module.driver.adc.virtual_channel_26_limit_clip_table_id.disabled" />
      <property id="module.driver.adc.virtual_channel_26_resolution_format" value="module.driver.adc.virtual_channel_26_resolution_format.12_bit_data_format" />
      <property id="module.driver.adc.virtual_channel_27_scan_group" value="module.driver.adc.virtual_channel_27_scan_group.none" />
      <property id="module.driver.adc.virtual_channel_27_channel_select" value="module.driver.adc.virtual_channel_27_channel_select.an000" />
      <property id="module.driver.adc.virtual_channel_27_sampling_table_id" value="module.driver.adc.virtual_channel_27_sampling_table_id.sampling_state_entry_0" />
      <property id="module.driver.adc.virtual_channel_27_gain_table" value="module.driver.adc.virtual_channel_27_gain_table.disabled" />
      <property id="module.driver.adc.virtual_channel_27_offset_table" value="module.driver.adc.virtual_channel_27_offset_table.disabled" />
      <property id="module.driver.adc.virtual_channel_27_add_average_mode" value="module.driver.adc.virtual_channel_27_add_average_mode.disabled" />
      <property id="module.driver.adc.virtual_channel_27_add_average_count" value="module.driver.adc.virtual_channel_27_add_average_count.1_time_conversion" />
      <property id="module.driver.adc.virtual_channel_27_limit_clip_table_id" value="module.driver.adc.virtual_channel_27_limit_clip_table_id.disabled" />
      <property id="module.driver.adc.virtual_channel_27_resolution_format" value="module.driver.adc.virtual_channel_27_resolution_format.12_bit_data_format" />
      <property id="module.driver.adc.virtual_channel_28_scan_group" value="module.driver.adc.virtual_channel_28_scan_group.none" />
      <property id="module.driver.adc.virtual_channel_28_channel_select" value="module.driver.adc.virtual_channel_28_channel_select.an000" />
      <property id="module.driver.adc.virtual_channel_28_sampling_table_id" value="module.driver.adc.virtual_channel_28_sampling_table_id.sampling_state_entry_0" />
      <property id="module.driver.adc.virtual_channel_28_gain_table" value="module.driver.adc.virtual_channel_28_gain_table.disabled" />
      <property id="module.driver.adc.virtual_channel_28_offset_table" value="module.driver.adc.virtual_channel_28_offset_table.disabled" />
      <property id="module.driver.adc.virtual_channel_28_add_average_mode" value="module.driver.adc.virtual_channel_28_add_average_mode.disabled" />
      <property id="module.driver.adc.virtual_channel_28_add_average_count" value="module.driver.adc.virtual_channel_28_add_average_count.1_time_conversion" />
      <property id="module.driver.adc.virtual_channel_28_limit_clip_table_id" value="module.driver.adc.virtual_channel_28_limit_clip_table_id.disabled" />
      <property id="module.driver.adc.virtual_channel_28_resolution_format" value="module.driver.adc.virtual_channel_28_resolution_format.12_bit_data_format" />
      <property id="module.driver.adc.virtual_channel_29_scan_group" value="module.driver.adc.virtual_channel_29_scan_group.none" />
      <property id="module.driver.adc.virtual_channel_29_channel_select" value="module.driver.adc.virtual_channel_29_channel_select.an000" />
      <property id="module.driver.adc.virtual_channel_29_sampling_table_id" value="module.driver.adc.virtual_channel_29_sampling_table_id.sampling_state_entry_0" />
      <property id="module.driver.adc.virtual_channel_29_gain_table" value="module.driver.adc.virtual_channel_29_gain_table.disabled" />
      <property id="module.driver.adc.virtual_channel_29_offset_table" value="module.driver.adc.virtual_channel_29_offset_table.disabled" />
      <property id="module.driver.adc.virtual_channel_29_add_average_mode" value="module.driver.adc.virtual_channel_29_add_average_mode.disabled" />
      <property id="module.driver.adc.virtual_channel_29_add_average_count" value="module.driver.adc.virtual_channel_29_add_average_count.1_time_conversion" />
      <property id="module.driver.adc.virtual_channel_29_limit_clip_table_id" value="module.driver.adc.virtual_channel_29_limit_clip_table_id.disabled" />
      <property id="module.driver.adc.virtual_channel_29_resolution_format" value="module.driver.adc.virtual_channel_29_resolution_format.12_bit_data_format" />
      <property id="module.driver.adc.virtual_channel_30_scan_group" value="module.driver.adc.virtual_channel_30_scan_group.none" />
      <property id="module.driver.adc.virtual_channel_30_channel_select" value="module.driver.adc.virtual_channel_30_channel_select.an000" />
      <property id="module.driver.adc.virtual_channel_30_sampling_table_id" value="module.driver.adc.virtual_channel_30_sampling_table_id.sampling_state_entry_0" />
      <property id="module.driver.adc.virtual_channel_30_gain_table" value="module.driver.adc.virtual_channel_30_gain_table.disabled" />
      <property id="module.driver.adc.virtual_channel_30_offset_table" value="module.driver.adc.virtual_channel_30_offset_table.disabled" />
      <property id="module.driver.adc.virtual_channel_30_add_average_mode" value="module.driver.adc.virtual_channel_30_add_average_mode.disabled" />
      <property id="module.driver.adc.virtual_channel_30_add_average_count" value="module.driver.adc.virtual_channel_30_add_average_count.1_time_conversion" />
      <property id="module.driver.adc.virtual_channel_30_limit_clip_table_id" value="module.driver.adc.virtual_channel_30_limit_clip_table_id.disabled" />
      <property id="module.driver.adc.virtual_channel_30_resolution_format" value="module.driver.adc.virtual_channel_30_resolution_format.12_bit_data_format" />
      <property id="module.driver.adc.virtual_channel_31_scan_group" value="module.driver.adc.virtual_channel_31_scan_group.none" />
      <property id="module.driver.adc.virtual_channel_31_channel_select" value="module.driver.adc.virtual_channel_31_channel_select.an000" />
      <property id="module.driver.adc.virtual_channel_31_sampling_table_id" value="module.driver.adc.virtual_channel_31_sampling_table_id.sampling_state_entry_0" />
      <property id="module.driver.adc.virtual_channel_31_gain_table" value="module.driver.adc.virtual_channel_31_gain_table.disabled" />
      <property id="module.driver.adc.virtual_channel_31_offset_table" value="module.driver.adc.virtual_channel_31_offset_table.disabled" />
      <property id="module.driver.adc.virtual_channel_31_add_average_mode" value="module.driver.adc.virtual_channel_31_add_average_mode.disabled" />
      <property id="module.driver.adc.virtual_channel_31_add_average_count" value="module.driver.adc.virtual_channel_31_add_average_count.1_time_conversion" />
      <property id="module.driver.adc.virtual_channel_31_limit_clip_table_id" value="module.driver.adc.virtual_channel_31_limit_clip_table_id.disabled" />
      <property id="module.driver.adc.virtual_channel_31_resolution_format" value="module.driver.adc.virtual_channel_31_resolution_format.12_bit_data_format" />
      <property id="module.driver.adc.virtual_channel_32_scan_group" value="module.driver.adc.virtual_channel_32_scan_group.none" />
      <property id="module.driver.adc.virtual_channel_32_channel_select" value="module.driver.adc.virtual_channel_32_channel_select.an000" />
      <property id="module.driver.adc.virtual_channel_32_sampling_table_id" value="module.driver.adc.virtual_channel_32_sampling_table_id.sampling_state_entry_0" />
      <property id="module.driver.adc.virtual_channel_32_gain_table" value="module.driver.adc.virtual_channel_32_gain_table.disabled" />
      <property id="module.driver.adc.virtual_channel_32_offset_table" value="module.driver.adc.virtual_channel_32_offset_table.disabled" />
      <property id="module.driver.adc.virtual_channel_32_add_average_mode" value="module.driver.adc.virtual_channel_32_add_average_mode.disabled" />
      <property id="module.driver.adc.virtual_channel_32_add_average_count" value="module.driver.adc.virtual_channel_32_add_average_count.1_time_conversion" />
      <property id="module.driver.adc.virtual_channel_32_limit_clip_table_id" value="module.driver.adc.virtual_channel_32_limit_clip_table_id.disabled" />
      <property id="module.driver.adc.virtual_channel_32_resolution_format" value="module.driver.adc.virtual_channel_32_resolution_format.12_bit_data_format" />
      <property id="module.driver.adc.virtual_channel_33_scan_group" value="module.driver.adc.virtual_channel_33_scan_group.none" />
      <property id="module.driver.adc.virtual_channel_33_channel_select" value="module.driver.adc.virtual_channel_33_channel_select.an000" />
      <property id="module.driver.adc.virtual_channel_33_sampling_table_id" value="module.driver.adc.virtual_channel_33_sampling_table_id.sampling_state_entry_0" />
      <property id="module.driver.adc.virtual_channel_33_gain_table" value="module.driver.adc.virtual_channel_33_gain_table.disabled" />
      <property id="module.driver.adc.virtual_channel_33_offset_table" value="module.driver.adc.virtual_channel_33_offset_table.disabled" />
      <property id="module.driver.adc.virtual_channel_33_add_average_mode" value="module.driver.adc.virtual_channel_33_add_average_mode.disabled" />
      <property id="module.driver.adc.virtual_channel_33_add_average_count" value="module.driver.adc.virtual_channel_33_add_average_count.1_time_conversion" />
      <property id="module.driver.adc.virtual_channel_33_limit_clip_table_id" value="module.driver.adc.virtual_channel_33_limit_clip_table_id.disabled" />
      <property id="module.driver.adc.virtual_channel_33_resolution_format" value="module.driver.adc.virtual_channel_33_resolution_format.12_bit_data_format" />
      <property id="module.driver.adc.virtual_channel_34_scan_group" value="module.driver.adc.virtual_channel_34_scan_group.none" />
      <property id="module.driver.adc.virtual_channel_34_channel_select" value="module.driver.adc.virtual_channel_34_channel_select.an000" />
      <property id="module.driver.adc.virtual_channel_34_sampling_table_id" value="module.driver.adc.virtual_channel_34_sampling_table_id.sampling_state_entry_0" />
      <property id="module.driver.adc.virtual_channel_34_gain_table" value="module.driver.adc.virtual_channel_34_gain_table.disabled" />
      <property id="module.driver.adc.virtual_channel_34_offset_table" value="module.driver.adc.virtual_channel_34_offset_table.disabled" />
      <property id="module.driver.adc.virtual_channel_34_add_average_mode" value="module.driver.adc.virtual_channel_34_add_average_mode.disabled" />
      <property id="module.driver.adc.virtual_channel_34_add_average_count" value="module.driver.adc.virtual_channel_34_add_average_count.1_time_conversion" />
      <property id="module.driver.adc.virtual_channel_34_limit_clip_table_id" value="module.driver.adc.virtual_channel_34_limit_clip_table_id.disabled" />
      <property id="module.driver.adc.virtual_channel_34_resolution_format" value="module.driver.adc.virtual_channel_34_resolution_format.12_bit_data_format" />
      <property id="module.driver.adc.virtual_channel_35_scan_group" value="module.driver.adc.virtual_channel_35_scan_group.none" />
      <property id="module.driver.adc.virtual_channel_35_channel_select" value="module.driver.adc.virtual_channel_35_channel_select.an000" />
      <property id="module.driver.adc.virtual_channel_35_sampling_table_id" value="module.driver.adc.virtual_channel_35_sampling_table_id.sampling_state_entry_0" />
      <property id="module.driver.adc.virtual_channel_35_gain_table" value="module.driver.adc.virtual_channel_35_gain_table.disabled" />
      <property id="module.driver.adc.virtual_channel_35_offset_table" value="module.driver.adc.virtual_channel_35_offset_table.disabled" />
      <property id="module.driver.adc.virtual_channel_35_add_average_mode" value="module.driver.adc.virtual_channel_35_add_average_mode.disabled" />
      <property id="module.driver.adc.virtual_channel_35_add_average_count" value="module.driver.adc.virtual_channel_35_add_average_count.1_time_conversion" />
      <property id="module.driver.adc.virtual_channel_35_limit_clip_table_id" value="module.driver.adc.virtual_channel_35_limit_clip_table_id.disabled" />
      <property id="module.driver.adc.virtual_channel_35_resolution_format" value="module.driver.adc.virtual_channel_35_resolution_format.12_bit_data_format" />
      <property id="module.driver.adc.virtual_channel_36_scan_group" value="module.driver.adc.virtual_channel_36_scan_group.none" />
      <property id="module.driver.adc.virtual_channel_36_channel_select" value="module.driver.adc.virtual_channel_36_channel_select.an000" />
      <property id="module.driver.adc.virtual_channel_36_sampling_table_id" value="module.driver.adc.virtual_channel_36_sampling_table_id.sampling_state_entry_0" />
      <property id="module.driver.adc.virtual_channel_36_gain_table" value="module.driver.adc.virtual_channel_36_gain_table.disabled" />
      <property id="module.driver.adc.virtual_channel_36_offset_table" value="module.driver.adc.virtual_channel_36_offset_table.disabled" />
      <property id="module.driver.adc.virtual_channel_36_add_average_mode" value="module.driver.adc.virtual_channel_36_add_average_mode.disabled" />
      <property id="module.driver.adc.virtual_channel_36_add_average_count" value="module.driver.adc.virtual_channel_36_add_average_count.1_time_conversion" />
      <property id="module.driver.adc.virtual_channel_36_limit_clip_table_id" value="module.driver.adc.virtual_channel_36_limit_clip_table_id.disabled" />
      <property id="module.driver.adc.virtual_channel_36_resolution_format" value="module.driver.adc.virtual_channel_36_resolution_format.12_bit_data_format" />
      <property id="module.driver.adc.scan_group_0_enable" value="module.driver.adc.scan_group_0_enable.enable" />
      <property id="module.driver.adc.scan_group_0_converter_selection" value="module.driver.adc.scan_group_0_converter_selection.adc_0" />
      <property id="module.driver.adc.scan_group_0_start_trigger_delay" value="0" />
      <property id="module.driver.adc.scan_group_0_self_diag_voltage" value="Disabled" />
      <property id="module.driver.adc.scan_group_0_scan_end_isr_enable" value="module.driver.adc.scan_group_0_scan_end_isr_enable.enable" />
      <property id="module.driver.adc.scan_group_0_external_trigger_enable_mask" value="" />
      <property id="module.driver.adc.scan_group_0_elc_trigger_enable_mask" value="" />
      <property id="module.driver.adc.scan_group_0_gpt_trigger_enable_mask" value="" />
      <property id="module.driver.adc.scan_group_0_limit_clip_isr_enable" value="module.driver.adc.scan_group_0_limit_clip_isr_enable.disable" />
      <property id="module.driver.adc.scan_group_0_fifo_enable" value="module.driver.adc.scan_group_0_fifo_enable.disable" />
      <property id="module.driver.adc.scan_group_0_fifo_isr_enable" value="module.driver.adc.scan_group_0_fifo_isr_enable.disable" />
      <property id="module.driver.adc.scan_group_0_fifo_isr_generation_level" value="0" />
      <property id="module.driver.adc.scan_group_1_enable" value="module.driver.adc.scan_group_1_enable.disable" />
      <property id="module.driver.adc.scan_group_1_converter_selection" value="module.driver.adc.scan_group_1_converter_selection.adc_0" />
      <property id="module.driver.adc.scan_group_1_start_trigger_delay" value="0" />
      <property id="module.driver.adc.scan_group_1_self_diag_voltage" value="Disabled" />
      <property id="module.driver.adc.scan_group_1_scan_end_isr_enable" value="module.driver.adc.scan_group_1_scan_end_isr_enable.enable" />
      <property id="module.driver.adc.scan_group_1_external_trigger_enable_mask" value="" />
      <property id="module.driver.adc.scan_group_1_elc_trigger_enable_mask" value="" />
      <property id="module.driver.adc.scan_group_1_gpt_trigger_enable_mask" value="" />
      <property id="module.driver.adc.scan_group_1_limit_clip_isr_enable" value="module.driver.adc.scan_group_1_limit_clip_isr_enable.enable" />
      <property id="module.driver.adc.scan_group_1_fifo_enable" value="module.driver.adc.scan_group_1_fifo_enable.disable" />
      <property id="module.driver.adc.scan_group_1_fifo_isr_enable" value="module.driver.adc.scan_group_1_fifo_isr_enable.disable" />
      <property id="module.driver.adc.scan_group_1_fifo_isr_generation_level" value="0" />
      <property id="module.driver.adc.scan_group_2_enable" value="module.driver.adc.scan_group_2_enable.disable" />
      <property id="module.driver.adc.scan_group_2_converter_selection" value="module.driver.adc.scan_group_2_converter_selection.adc_0" />
      <property id="module.driver.adc.scan_group_2_start_trigger_delay" value="0" />
      <property id="module.driver.adc.scan_group_2_self_diag_voltage" value="Disabled" />
      <property id="module.driver.adc.scan_group_2_scan_end_isr_enable" value="module.driver.adc.scan_group_2_scan_end_isr_enable.enable" />
      <property id="module.driver.adc.scan_group_2_external_trigger_enable_mask" value="" />
      <property id="module.driver.adc.scan_group_2_elc_trigger_enable_mask" value="" />
      <property id="module.driver.adc.scan_group_2_gpt_trigger_enable_mask" value="" />
      <property id="module.driver.adc.scan_group_2_limit_clip_isr_enable" value="module.driver.adc.scan_group_2_limit_clip_isr_enable.enable" />
      <property id="module.driver.adc.scan_group_2_fifo_enable" value="module.driver.adc.scan_group_2_fifo_enable.disable" />
      <property id="module.driver.adc.scan_group_2_fifo_isr_enable" value="module.driver.adc.scan_group_2_fifo_isr_enable.disable" />
      <property id="module.driver.adc.scan_group_2_fifo_isr_generation_level" value="0" />
      <property id="module.driver.adc.scan_group_3_enable" value="module.driver.adc.scan_group_3_enable.disable" />
      <property id="module.driver.adc.scan_group_3_converter_selection" value="module.driver.adc.scan_group_3_converter_selection.adc_0" />
      <property id="module.driver.adc.scan_group_3_start_trigger_delay" value="0" />
      <property id="module.driver.adc.scan_group_3_self_diag_voltage" value="Disabled" />
      <property id="module.driver.adc.scan_group_3_scan_end_isr_enable" value="module.driver.adc.scan_group_3_scan_end_isr_enable.enable" />
      <property id="module.driver.adc.scan_group_3_external_trigger_enable_mask" value="" />
      <property id="module.driver.adc.scan_group_3_elc_trigger_enable_mask" value="" />
      <property id="module.driver.adc.scan_group_3_gpt_trigger_enable_mask" value="" />
      <property id="module.driver.adc.scan_group_3_limit_clip_isr_enable" value="module.driver.adc.scan_group_3_limit_clip_isr_enable.enable" />
      <property id="module.driver.adc.scan_group_3_fifo_enable" value="module.driver.adc.scan_group_3_fifo_enable.disable" />
      <property id="module.driver.adc.scan_group_3_fifo_isr_enable" value="module.driver.adc.scan_group_3_fifo_isr_enable.disable" />
      <property id="module.driver.adc.scan_group_3_fifo_isr_generation_level" value="0" />
      <property id="module.driver.adc.scan_group_4_enable" value="module.driver.adc.scan_group_4_enable.disable" />
      <property id="module.driver.adc.scan_group_4_converter_selection" value="module.driver.adc.scan_group_4_converter_selection.adc_0" />
      <property id="module.driver.adc.scan_group_4_start_trigger_delay" value="0" />
      <property id="module.driver.adc.scan_group_4_self_diag_voltage" value="Disabled" />
      <property id="module.driver.adc.scan_group_4_scan_end_isr_enable" value="module.driver.adc.scan_group_4_scan_end_isr_enable.enable" />
      <property id="module.driver.adc.scan_group_4_external_trigger_enable_mask" value="" />
      <property id="module.driver.adc.scan_group_4_elc_trigger_enable_mask" value="" />
      <property id="module.driver.adc.scan_group_4_gpt_trigger_enable_mask" value="" />
      <property id="module.driver.adc.scan_group_4_limit_clip_isr_enable" value="module.driver.adc.scan_group_4_limit_clip_isr_enable.enable" />
      <property id="module.driver.adc.scan_group_4_fifo_enable" value="module.driver.adc.scan_group_4_fifo_enable.disable" />
      <property id="module.driver.adc.scan_group_4_fifo_isr_enable" value="module.driver.adc.scan_group_4_fifo_isr_enable.disable" />
      <property id="module.driver.adc.scan_group_4_fifo_isr_generation_level" value="0" />
      <property id="module.driver.adc.scan_group_5_enable" value="module.driver.adc.scan_group_5_enable.disable" />
      <property id="module.driver.adc.scan_group_5_converter_selection" value="module.driver.adc.scan_group_5_converter_selection.adc_0" />
      <property id="module.driver.adc.scan_group_5_start_trigger_delay" value="0" />
      <property id="module.driver.adc.scan_group_5_self_diag_voltage" value="Disabled" />
      <property id="module.driver.adc.scan_group_5_scan_end_isr_enable" value="module.driver.adc.scan_group_5_scan_end_isr_enable.enable" />
      <property id="module.driver.adc.scan_group_5_external_trigger_enable_mask" value="" />
      <property id="module.driver.adc.scan_group_5_elc_trigger_enable_mask" value="" />
      <property id="module.driver.adc.scan_group_5_gpt_trigger_enable_mask" value="" />
      <property id="module.driver.adc.scan_group_5_limit_clip_isr_enable" value="module.driver.adc.scan_group_5_limit_clip_isr_enable.enable" />
      <property id="module.driver.adc.scan_group_5_fifo_enable" value="module.driver.adc.scan_group_5_fifo_enable.disable" />
      <property id="module.driver.adc.scan_group_5_fifo_isr_enable" value="module.driver.adc.scan_group_5_fifo_isr_enable.disable" />
      <property id="module.driver.adc.scan_group_5_fifo_isr_generation_level" value="0" />
      <property id="module.driver.adc.scan_group_6_enable" value="module.driver.adc.scan_group_6_enable.disable" />
      <property id="module.driver.adc.scan_group_6_converter_selection" value="module.driver.adc.scan_group_6_converter_selection.adc_0" />
      <property id="module.driver.adc.scan_group_6_start_trigger_delay" value="0" />
      <property id="module.driver.adc.scan_group_6_self_diag_voltage" value="Disabled" />
      <property id="module.driver.adc.scan_group_6_scan_end_isr_enable" value="module.driver.adc.scan_group_6_scan_end_isr_enable.enable" />
      <property id="module.driver.adc.scan_group_6_external_trigger_enable_mask" value="" />
      <property id="module.driver.adc.scan_group_6_elc_trigger_enable_mask" value="" />
      <property id="module.driver.adc.scan_group_6_gpt_trigger_enable_mask" value="" />
      <property id="module.driver.adc.scan_group_6_limit_clip_isr_enable" value="module.driver.adc.scan_group_6_limit_clip_isr_enable.enable" />
      <property id="module.driver.adc.scan_group_6_fifo_enable" value="module.driver.adc.scan_group_6_fifo_enable.disable" />
      <property id="module.driver.adc.scan_group_6_fifo_isr_enable" value="module.driver.adc.scan_group_6_fifo_isr_enable.disable" />
      <property id="module.driver.adc.scan_group_6_fifo_isr_generation_level" value="0" />
      <property id="module.driver.adc.scan_group_7_enable" value="module.driver.adc.scan_group_7_enable.disable" />
      <property id="module.driver.adc.scan_group_7_converter_selection" value="module.driver.adc.scan_group_7_converter_selection.adc_0" />
      <property id="module.driver.adc.scan_group_7_start_trigger_delay" value="0" />
      <property id="module.driver.adc.scan_group_7_self_diag_voltage" value="Disabled" />
      <property id="module.driver.adc.scan_group_7_scan_end_isr_enable" value="module.driver.adc.scan_group_7_scan_end_isr_enable.enable" />
      <property id="module.driver.adc.scan_group_7_external_trigger_enable_mask" value="" />
      <property id="module.driver.adc.scan_group_7_elc_trigger_enable_mask" value="" />
      <property id="module.driver.adc.scan_group_7_gpt_trigger_enable_mask" value="" />
      <property id="module.driver.adc.scan_group_7_limit_clip_isr_enable" value="module.driver.adc.scan_group_7_limit_clip_isr_enable.enable" />
      <property id="module.driver.adc.scan_group_7_fifo_enable" value="module.driver.adc.scan_group_7_fifo_enable.disable" />
      <property id="module.driver.adc.scan_group_7_fifo_isr_enable" value="module.driver.adc.scan_group_7_fifo_isr_enable.disable" />
      <property id="module.driver.adc.scan_group_7_fifo_isr_generation_level" value="0" />
      <property id="module.driver.adc.scan_group_8_enable" value="module.driver.adc.scan_group_8_enable.disable" />
      <property id="module.driver.adc.scan_group_8_converter_selection" value="module.driver.adc.scan_group_8_converter_selection.adc_0" />
      <property id="module.driver.adc.scan_group_8_start_trigger_delay" value="0" />
      <property id="module.driver.adc.scan_group_8_self_diag_voltage" value="Disabled" />
      <property id="module.driver.adc.scan_group_8_scan_end_isr_enable" value="module.driver.adc.scan_group_8_scan_end_isr_enable.enable" />
      <property id="module.driver.adc.scan_group_8_external_trigger_enable_mask" value="" />
      <property id="module.driver.adc.scan_group_8_elc_trigger_enable_mask" value="" />
      <property id="module.driver.adc.scan_group_8_gpt_trigger_enable_mask" value="" />
      <property id="module.driver.adc.scan_group_8_limit_clip_isr_enable" value="module.driver.adc.scan_group_8_limit_clip_isr_enable.enable" />
      <property id="module.driver.adc.scan_group_8_fifo_enable" value="module.driver.adc.scan_group_8_fifo_enable.disable" />
      <property id="module.driver.adc.scan_group_8_fifo_isr_enable" value="module.driver.adc.scan_group_8_fifo_isr_enable.disable" />
      <property id="module.driver.adc.scan_group_8_fifo_isr_generation_level" value="0" />
    </module>
    <context id="_hal.0">
      <stack module="module.driver.ioport_on_ioport.0" />
      <stack module="module.driver.adc_on_adc_b.2092153079" />
    </context>
    <config id="config.driver.ioport">
      <property id="config.driver.ioport.checking" value="config.driver.ioport.checking.system" />
    </config>
    <config id="config.driver.adc_b">
      <property id="config.driver.adc.param_checking_enable" value="bsp" />
    </config>
  </raModuleConfiguration>
  <raPinConfiguration>
    <pincfg active="true" name="RA6T2-MCK.pincfg" selected="true" symbol="g_bsp_pin_cfg">
      <configSetting altId="gpt2.gtioc2a.pd08" configurationId="gpt2.gtioc2a" />
      <configSetting altId="gpt2.gtioc2b.pd09" configurationId="gpt2.gtioc2b" />
      <configSetting altId="gpt2.mode.gtiocaandgtiocb.free" configurationId="gpt2.mode" />
      <configSetting altId="gpt3.gtioc3a.pc14" configurationId="gpt3.gtioc3a" />
      <configSetting altId="gpt3.gtioc3b.pc15" configurationId="gpt3.gtioc3b" />
      <configSetting altId="gpt3.mode.gtiocaandgtiocb.free" configurationId="gpt3.mode" />
      <configSetting altId="gpt4.gtioc4a.pb04" configurationId="gpt4.gtioc4a" />
      <configSetting altId="gpt4.gtioc4b.pb05" configurationId="gpt4.gtioc4b" />
      <configSetting altId="gpt4.mode.gtiocaandgtiocb.free" configurationId="gpt4.mode" />
      <configSetting altId="gpt5.gtioc5a.pb06" configurationId="gpt5.gtioc5a" />
      <configSetting altId="gpt5.gtioc5b.pb07" configurationId="gpt5.gtioc5b" />
      <configSetting altId="gpt5.mode.gtiocaandgtiocb.free" configurationId="gpt5.mode" />
      <configSetting altId="gpt6.gtioc6a.pb08" configurationId="gpt6.gtioc6a" />
      <configSetting altId="gpt6.gtioc6b.pb09" configurationId="gpt6.gtioc6b" />
      <configSetting altId="gpt6.mode.gtiocaandgtiocb.free" configurationId="gpt6.mode" />
      <configSetting altId="gpt7.gtioc7a.pc08" configurationId="gpt7.gtioc7a" />
      <configSetting altId="gpt7.gtioc7b.pc09" configurationId="gpt7.gtioc7b" />
      <configSetting altId="gpt7.mode.gtiocaandgtiocb.free" configurationId="gpt7.mode" />
      <configSetting altId="gpt8.gtioc8a.pa08" configurationId="gpt8.gtioc8a" />
      <configSetting altId="gpt8.gtioc8b_a.pa09" configurationId="gpt8.gtioc8b" />
      <configSetting altId="gpt8.mode.gtiocaandgtiocb.free" configurationId="gpt8.mode" />
      <configSetting altId="gpt9.gtioc9a.pa10" configurationId="gpt9.gtioc9a" />
      <configSetting altId="gpt9.gtioc9b.pa11" configurationId="gpt9.gtioc9b" />
      <configSetting altId="gpt9.mode.gtiocaandgtiocb.free" configurationId="gpt9.mode" />
      <configSetting altId="gpt_poegb.gtetrgb.pa12" configurationId="gpt_poegb.gtetrgb" />
      <configSetting altId="gpt_poegb.mode.enabled.free" configurationId="gpt_poegb.mode" />
      <configSetting altId="gpt_poegd.gtetrgd.pc13" configurationId="gpt_poegd.gtetrgd" />
      <configSetting altId="gpt_poegd.mode.enabled.free" configurationId="gpt_poegd.mode" />
      <configSetting altId="jtag_fslash_swd.mode.jtag.free" configurationId="jtag_fslash_swd.mode" />
      <configSetting altId="jtag_fslash_swd.tck.pa14" configurationId="jtag_fslash_swd.tck" />
      <configSetting altId="jtag_fslash_swd.tdi.pa15" configurationId="jtag_fslash_swd.tdi" />
      <configSetting altId="jtag_fslash_swd.tdo.pb03" configurationId="jtag_fslash_swd.tdo" />
      <configSetting altId="jtag_fslash_swd.tms.pa13" configurationId="jtag_fslash_swd.tms" />
      <configSetting altId="pa08.gpt8.gtioc8a" configurationId="pa08" />
      <configSetting altId="pa08.gpio_mode.gpio_mode_peripheral" configurationId="pa08.gpio_mode" />
      <configSetting altId="pa09.gpt8.gtioc8b_a" configurationId="pa09" />
      <configSetting altId="pa09.gpio_mode.gpio_mode_peripheral" configurationId="pa09.gpio_mode" />
      <configSetting altId="pa10.gpt9.gtioc9a" configurationId="pa10" />
      <configSetting altId="pa10.gpio_mode.gpio_mode_peripheral" configurationId="pa10.gpio_mode" />
      <configSetting altId="pa11.gpt9.gtioc9b" configurationId="pa11" />
      <configSetting altId="pa11.gpio_mode.gpio_mode_peripheral" configurationId="pa11.gpio_mode" />
      <configSetting altId="pa12.gpt_poegb.gtetrgb" configurationId="pa12" />
      <configSetting altId="pa12.gpio_mode.gpio_mode_peripheral" configurationId="pa12.gpio_mode" />
      <configSetting altId="pa13.jtag_fslash_swd.tms" configurationId="pa13" />
      <configSetting altId="pa13.gpio_mode.gpio_mode_peripheral" configurationId="pa13.gpio_mode" />
      <configSetting altId="pa14.jtag_fslash_swd.tck" configurationId="pa14" />
      <configSetting altId="pa14.gpio_mode.gpio_mode_peripheral" configurationId="pa14.gpio_mode" />
      <configSetting altId="pa15.jtag_fslash_swd.tdi" configurationId="pa15" />
      <configSetting altId="pa15.gpio_mode.gpio_mode_peripheral" configurationId="pa15.gpio_mode" />
      <configSetting altId="pb01.input" configurationId="pb01" />
      <configSetting altId="pb01.gpio_irq.gpio_irq_enabled" configurationId="pb01.gpio_irq" />
      <configSetting altId="pb01.gpio_mode.gpio_mode_in" configurationId="pb01.gpio_mode" />
      <configSetting altId="pb03.jtag_fslash_swd.tdo" configurationId="pb03" />
      <configSetting altId="pb03.gpio_mode.gpio_mode_peripheral" configurationId="pb03.gpio_mode" />
      <configSetting altId="pb04.gpt4.gtioc4a" configurationId="pb04" />
      <configSetting altId="pb04.gpio_mode.gpio_mode_peripheral" configurationId="pb04.gpio_mode" />
      <configSetting altId="pb05.gpt4.gtioc4b" configurationId="pb05" />
      <configSetting altId="pb05.gpio_mode.gpio_mode_peripheral" configurationId="pb05.gpio_mode" />
      <configSetting altId="pb06.gpt5.gtioc5a" configurationId="pb06" />
      <configSetting altId="pb06.gpio_mode.gpio_mode_peripheral" configurationId="pb06.gpio_mode" />
      <configSetting altId="pb07.gpt5.gtioc5b" configurationId="pb07" />
      <configSetting altId="pb07.gpio_mode.gpio_mode_peripheral" configurationId="pb07.gpio_mode" />
      <configSetting altId="pb08.gpt6.gtioc6a" configurationId="pb08" />
      <configSetting altId="pb08.gpio_mode.gpio_mode_peripheral" configurationId="pb08.gpio_mode" />
      <configSetting altId="pb09.gpt6.gtioc6b" configurationId="pb09" />
      <configSetting altId="pb09.gpio_mode.gpio_mode_peripheral" configurationId="pb09.gpio_mode" />
      <configSetting altId="pc00.input" configurationId="pc00" />
      <configSetting altId="pc00.gpio_mode.gpio_mode_in" configurationId="pc00.gpio_mode" />
      <configSetting altId="pc01.input" configurationId="pc01" />
      <configSetting altId="pc01.gpio_mode.gpio_mode_in" configurationId="pc01.gpio_mode" />
      <configSetting altId="pc04.input" configurationId="pc04" />
      <configSetting altId="pc04.gpio_irq.gpio_irq_enabled" configurationId="pc04.gpio_irq" />
      <configSetting altId="pc04.gpio_mode.gpio_mode_in" configurationId="pc04.gpio_mode" />
      <configSetting altId="pc05.input" configurationId="pc05" />
      <configSetting altId="pc05.gpio_irq.gpio_irq_enabled" configurationId="pc05.gpio_irq" />
      <configSetting altId="pc05.gpio_mode.gpio_mode_in" configurationId="pc05.gpio_mode" />
      <configSetting altId="pc06.output.high" configurationId="pc06" />
      <configSetting altId="pc06.gpio_mode.gpio_mode_out.high" configurationId="pc06.gpio_mode" />
      <configSetting altId="pc07.output.high" configurationId="pc07" />
      <configSetting altId="pc07.gpio_mode.gpio_mode_out.high" configurationId="pc07.gpio_mode" />
      <configSetting altId="pc08.gpt7.gtioc7a" configurationId="pc08" />
      <configSetting altId="pc08.gpio_mode.gpio_mode_peripheral" configurationId="pc08.gpio_mode" />
      <configSetting altId="pc09.gpt7.gtioc7b" configurationId="pc09" />
      <configSetting altId="pc09.gpio_mode.gpio_mode_peripheral" configurationId="pc09.gpio_mode" />
      <configSetting altId="pc13.gpt_poegd.gtetrgd" configurationId="pc13" />
      <configSetting altId="pc13.gpio_mode.gpio_mode_peripheral" configurationId="pc13.gpio_mode" />
      <configSetting altId="pc14.gpt3.gtioc3a" configurationId="pc14" />
      <configSetting altId="pc14.gpio_mode.gpio_mode_peripheral" configurationId="pc14.gpio_mode" />
      <configSetting altId="pc15.gpt3.gtioc3b" configurationId="pc15" />
      <configSetting altId="pc15.gpio_mode.gpio_mode_peripheral" configurationId="pc15.gpio_mode" />
      <configSetting altId="pd01.output.high" configurationId="pd01" />
      <configSetting altId="pd01.gpio_mode.gpio_mode_out.high" configurationId="pd01.gpio_mode" />
      <configSetting altId="pd02.output.high" configurationId="pd02" />
      <configSetting altId="pd02.gpio_mode.gpio_mode_out.high" configurationId="pd02.gpio_mode" />
      <configSetting altId="pd03.output.high" configurationId="pd03" />
      <configSetting altId="pd03.gpio_mode.gpio_mode_out.high" configurationId="pd03.gpio_mode" />
      <configSetting altId="pd04.input" configurationId="pd04" />
      <configSetting altId="pd04.gpio_mode.gpio_mode_in" configurationId="pd04.gpio_mode" />
      <configSetting altId="pd07.input" configurationId="pd07" />
      <configSetting altId="pd07.gpio_mode.gpio_mode_in" configurationId="pd07.gpio_mode" />
      <configSetting altId="pd08.gpt2.gtioc2a" configurationId="pd08" />
      <configSetting altId="pd08.gpio_mode.gpio_mode_peripheral" configurationId="pd08.gpio_mode" />
      <configSetting altId="pd09.gpt2.gtioc2b" configurationId="pd09" />
      <configSetting altId="pd09.gpio_mode.gpio_mode_peripheral" configurationId="pd09.gpio_mode" />
      <configSetting altId="pd12.input" configurationId="pd12" />
      <configSetting altId="pd12.gpio_irq.gpio_irq_enabled" configurationId="pd12.gpio_irq" />
      <configSetting altId="pd12.gpio_mode.gpio_mode_in" configurationId="pd12.gpio_mode" />
      <configSetting altId="pd13.input" configurationId="pd13" />
      <configSetting altId="pd13.gpio_irq.gpio_irq_enabled" configurationId="pd13.gpio_irq" />
      <configSetting altId="pd13.gpio_mode.gpio_mode_in" configurationId="pd13.gpio_mode" />
      <configSetting altId="pd14.input" configurationId="pd14" />
      <configSetting altId="pd14.gpio_irq.gpio_irq_enabled" configurationId="pd14.gpio_irq" />
      <configSetting altId="pd14.gpio_mode.gpio_mode_in" configurationId="pd14.gpio_mode" />
      <configSetting altId="pd15.output.high" configurationId="pd15" />
      <configSetting altId="pd15.gpio_mode.gpio_mode_out.high" configurationId="pd15.gpio_mode" />
    </pincfg>
    <pincfg active="false" name="R7FA6T2BD3CFP.pincfg" selected="false" symbol="">
      <configSetting altId="jtag_fslash_swd.mode.jtag.free" configurationId="jtag_fslash_swd.mode" />
      <configSetting altId="jtag_fslash_swd.tck.pa14" configurationId="jtag_fslash_swd.tck" />
      <configSetting altId="jtag_fslash_swd.tdi.pa15" configurationId="jtag_fslash_swd.tdi" />
      <configSetting altId="jtag_fslash_swd.tdo.pb03" configurationId="jtag_fslash_swd.tdo" />
      <configSetting altId="jtag_fslash_swd.tms.pa13" configurationId="jtag_fslash_swd.tms" />
      <configSetting altId="pa13.jtag_fslash_swd.tms" configurationId="pa13" />
      <configSetting altId="pa13.gpio_mode.gpio_mode_peripheral" configurationId="pa13.gpio_mode" />
      <configSetting altId="pa14.jtag_fslash_swd.tck" configurationId="pa14" />
      <configSetting altId="pa14.gpio_mode.gpio_mode_peripheral" configurationId="pa14.gpio_mode" />
      <configSetting altId="pa15.jtag_fslash_swd.tdi" configurationId="pa15" />
      <configSetting altId="pa15.gpio_mode.gpio_mode_peripheral" configurationId="pa15.gpio_mode" />
      <configSetting altId="pb03.jtag_fslash_swd.tdo" configurationId="pb03" />
      <configSetting altId="pb03.gpio_mode.gpio_mode_peripheral" configurationId="pb03.gpio_mode" />
    </pincfg>
  </raPinConfiguration>
</raConfiguration>