<?xml version="1.0" encoding="UTF-8" standalone="no"?>
<raConfiguration version="6">
  <generalSettings>
    <option key="#Board#" value="board.ra6m2ek" />
    <option key="CPU" value="RA6M2" />
    <option key="#TargetName#" value="R7FA6M2AF3CFB" />
    <option key="#TargetARCHITECTURE#" value="cortex-m4" />
    <option key="#DeviceCommand#" value="R7FA6M2AF" />
    <option key="#RTOS#" value="rtos.awsfreertos" />
    <option key="#pinconfiguration#" value="RA6M2-EK.pincfg" />
    <option key="#FSPVersion#" value="3.5.0" />
    <option key="#ConfigurationFragments#" value="Renesas##BSP##Board##ra6m2_ek##" />
    <option key="#SELECTED_TOOLCHAIN#" value="gcc-arm-embedded" />
    <option key="#ToolchainVersion#" value="9.2.1.20191025" />
  </generalSettings>
  <raBspConfiguration>
    <config id="config.bsp.ra6m2.R7FA6M2AF3CFB">
      <property id="config.bsp.part_number" value="config.bsp.part_number.value" />
      <property id="config.bsp.rom_size_bytes" value="config.bsp.rom_size_bytes.value" />
      <property id="config.bsp.rom_size_bytes_hidden" value="1048576" />
      <property id="config.bsp.ram_size_bytes" value="config.bsp.ram_size_bytes.value" />
      <property id="config.bsp.data_flash_size_bytes" value="config.bsp.data_flash_size_bytes.value" />
      <property id="config.bsp.package_style" value="config.bsp.package_style.value" />
      <property id="config.bsp.package_pins" value="config.bsp.package_pins.value" />
    </config>
    <config id="config.bsp.ra6m2">
      <property id="config.bsp.series" value="config.bsp.series.value" />
    </config>
    <config id="config.bsp.ra6m2.fsp">
      <property id="config.bsp.fsp.OFS0.iwdt_start_mode" value="config.bsp.fsp.OFS0.iwdt_start_mode.disabled" />
      <property id="config.bsp.fsp.OFS0.iwdt_timeout" value="config.bsp.fsp.OFS0.iwdt_timeout.2048" />
      <property id="config.bsp.fsp.OFS0.iwdt_divisor" value="config.bsp.fsp.OFS0.iwdt_divisor.128" />
      <property id="config.bsp.fsp.OFS0.iwdt_window_end" value="config.bsp.fsp.OFS0.iwdt_window_end.0" />
      <property id="config.bsp.fsp.OFS0.iwdt_window_start" value="config.bsp.fsp.OFS0.iwdt_window_start.100" />
      <property id="config.bsp.fsp.OFS0.iwdt_reset_interrupt" value="config.bsp.fsp.OFS0.iwdt_reset_interrupt.Reset" />
      <property id="config.bsp.fsp.OFS0.iwdt_stop_control" value="config.bsp.fsp.OFS0.iwdt_stop_control.stops" />
      <property id="config.bsp.fsp.OFS0.wdt_start_mode" value="config.bsp.fsp.OFS0.wdt_start_mode.register" />
      <property id="config.bsp.fsp.OFS0.wdt_timeout" value="config.bsp.fsp.OFS0.wdt_timeout.16384" />
      <property id="config.bsp.fsp.OFS0.wdt_divisor" value="config.bsp.fsp.OFS0.wdt_divisor.128" />
      <property id="config.bsp.fsp.OFS0.wdt_window_end" value="config.bsp.fsp.OFS0.wdt_window_end.0" />
      <property id="config.bsp.fsp.OFS0.wdt_window_start" value="config.bsp.fsp.OFS0.wdt_window_start.100" />
      <property id="config.bsp.fsp.OFS0.wdt_reset_interrupt" value="config.bsp.fsp.OFS0.wdt_reset_interrupt.Reset" />
      <property id="config.bsp.fsp.OFS0.wdt_stop_control" value="config.bsp.fsp.OFS0.wdt_stop_control.stops" />
      <property id="config.bsp.fsp.OFS1.voltage_detection0.start" value="config.bsp.fsp.OFS1.voltage_detection0.start.disabled" />
      <property id="config.bsp.fsp.OFS1.voltage_detection0_level" value="config.bsp.fsp.OFS1.voltage_detection0_level.280" />
      <property id="config.bsp.fsp.OFS1.hoco_osc" value="config.bsp.fsp.OFS1.hoco_osc.disabled" />
      <property id="config.bsp.fsp.mpu_pc0_enable" value="config.bsp.fsp.mpu_pc0_enable.disabled" />
      <property id="config.bsp.fsp.mpu_pc0_start" value="0xFFFFFFFC" />
      <property id="config.bsp.fsp.mpu_pc0_end" value="0xFFFFFFFF" />
      <property id="config.bsp.fsp.mpu_pc1_enable" value="config.bsp.fsp.mpu_pc1_enable.disabled" />
      <property id="config.bsp.fsp.mpu_pc1_start" value="0xFFFFFFFC" />
      <property id="config.bsp.fsp.mpu_pc1_end" value="0xFFFFFFFF" />
      <property id="config.bsp.fsp.mpu_reg0_enable" value="config.bsp.fsp.mpu_reg0_enable.disabled" />
      <property id="config.bsp.fsp.mpu_reg0_start" value="0x00FFFFFC" />
      <property id="config.bsp.fsp.mpu_reg0_end" value="0x00FFFFFF" />
      <property id="config.bsp.fsp.mpu_reg1_enable" value="config.bsp.fsp.mpu_reg1_enable.disabled" />
      <property id="config.bsp.fsp.mpu_reg1_start" value="0x200FFFFC" />
      <property id="config.bsp.fsp.mpu_reg1_end" value="0x200FFFFF" />
      <property id="config.bsp.fsp.mpu_reg2_enable" value="config.bsp.fsp.mpu_reg2_enable.disabled" />
      <property id="config.bsp.fsp.mpu_reg2_start" value="0x407FFFFC" />
      <property id="config.bsp.fsp.mpu_reg2_end" value="0x407FFFFF" />
      <property id="config.bsp.fsp.mpu_reg3_enable" value="config.bsp.fsp.mpu_reg3_enable.disabled" />
      <property id="config.bsp.fsp.mpu_reg3_start" value="0x400DFFFC" />
      <property id="config.bsp.fsp.mpu_reg3_end" value="0x400DFFFF" />
      <property id="config.bsp.fsp.hoco_fll" value="config.bsp.fsp.hoco_fll.disabled" />
      <property id="config.bsp.common.main_osc_wait" value="config.bsp.common.main_osc_wait.wait_8163" />
      <property id="config.bsp.fsp.mcu.adc.max_freq_hz" value="60000000" />
      <property id="config.bsp.fsp.mcu.sci_uart.max_baud" value="20000000" />
      <property id="config.bsp.fsp.mcu.adc.sample_and_hold" value="1" />
      <property id="config.bsp.fsp.mcu.sci_spi.max_bitrate" value="30000000" />
      <property id="config.bsp.fsp.mcu.spi.max_bitrate" value="30000000" />
      <property id="config.bsp.fsp.mcu.iic_master.rate.rate_fastplus" value="1" />
      <property id="config.bsp.common.id_mode" value="config.bsp.common.id_mode.unlocked" />
      <property id="config.bsp.common.id_code" value="FFFFFFFFFFFFFFFFFFFFFFFFFFFFFFFF" />
      <property id="config.bsp.common.id1" value="" />
      <property id="config.bsp.common.id2" value="" />
      <property id="config.bsp.common.id3" value="" />
      <property id="config.bsp.common.id4" value="" />
      <property id="config.bsp.common.id_fixed" value="" />
    </config>
    <config id="config.bsp.ra">
      <property id="config.bsp.common.main" value="0x400" />
      <property id="config.bsp.common.heap" value="0x1000" />
      <property id="config.bsp.common.vcc" value="3300" />
      <property id="config.bsp.common.checking" value="config.bsp.common.checking.enabled" />
      <property id="config.bsp.common.assert" value="config.bsp.common.assert.none" />
      <property id="config.bsp.common.error_log" value="config.bsp.common.error_log.none" />
      <property id="config.bsp.common.soft_reset" value="config.bsp.common.soft_reset.disabled" />
      <property id="config.bsp.common.main_osc_populated" value="config.bsp.common.main_osc_populated.enabled" />
      <property id="config.bsp.common.pfs_protect" value="config.bsp.common.pfs_protect.enabled" />
      <property id="config.bsp.common.c_runtime_init" value="config.bsp.common.c_runtime_init.enabled" />
      <property id="config.bsp.common.main_osc_clock_source" value="config.bsp.common.main_osc_clock_source.crystal" />
      <property id="config.bsp.common.subclock_populated" value="config.bsp.common.subclock_populated.enabled" />
      <property id="config.bsp.common.subclock_drive" value="config.bsp.common.subclock_drive.standard" />
      <property id="config.bsp.common.subclock_stabilization_ms" value="1000" />
    </config>
  </raBspConfiguration>
  <raClockConfiguration>
    <node id="board.clock.xtal.freq" mul="12000000" option="_edit" />
    <node id="board.clock.pll.source" option="board.clock.pll.source.xtal" />
    <node id="board.clock.hoco.freq" option="board.clock.hoco.freq.20m" />
    <node id="board.clock.loco.freq" option="board.clock.loco.freq.32768" />
    <node id="board.clock.moco.freq" option="board.clock.moco.freq.8m" />
    <node id="board.clock.subclk.freq" option="board.clock.subclk.freq.32768" />
    <node id="board.clock.pll.div" option="board.clock.pll.div.1" />
    <node id="board.clock.pll.mul" option="board.clock.pll.mul.200" />
    <node id="board.clock.pll.display" option="board.clock.pll.display.value" />
    <node id="board.clock.clock.source" option="board.clock.clock.source.pll" />
    <node id="board.clock.iclk.div" option="board.clock.iclk.div.2" />
    <node id="board.clock.iclk.display" option="board.clock.iclk.display.value" />
    <node id="board.clock.pclka.div" option="board.clock.pclka.div.2" />
    <node id="board.clock.pclka.display" option="board.clock.pclka.display.value" />
    <node id="board.clock.pclkb.div" option="board.clock.pclkb.div.4" />
    <node id="board.clock.pclkb.display" option="board.clock.pclkb.display.value" />
    <node id="board.clock.pclkc.div" option="board.clock.pclkc.div.4" />
    <node id="board.clock.pclkc.display" option="board.clock.pclkc.display.value" />
    <node id="board.clock.pclkd.div" option="board.clock.pclkd.div.2" />
    <node id="board.clock.pclkd.display" option="board.clock.pclkd.display.value" />
    <node id="board.clock.sdclkout.div" option="board.clock.sdclkout.div.1" />
    <node id="board.clock.sdclkout.display" option="board.clock.sdclkout.display.value" />
    <node id="board.clock.bclk.div" option="board.clock.bclk.div.2" />
    <node id="board.clock.bclk.display" option="board.clock.bclk.display.value" />
    <node id="board.clock.bclkout.div" option="board.clock.bclkout.div.2" />
    <node id="board.clock.bclkout.display" option="board.clock.bclkout.display.value" />
    <node id="board.clock.uclk.div" option="board.clock.uclk.div.5" />
    <node id="board.clock.uclk.display" option="board.clock.uclk.display.value" />
    <node id="board.clock.fclk.div" option="board.clock.fclk.div.4" />
    <node id="board.clock.fclk.display" option="board.clock.fclk.display.value" />
    <node id="board.clock.clkout.source" option="board.clock.clkout.source.disabled" />
    <node id="board.clock.clkout.div" option="board.clock.clkout.div.1" />
    <node id="board.clock.clkout.display" option="board.clock.clkout.display.value" />
  </raClockConfiguration>
  <raComponentSelection>
    <component apiversion="" class="RTOS" condition="" group="FreeRTOS" subgroup="all" variant="" vendor="AWS" version="10.4.3-LTS.Patch.2+fsp.3.5.0">
      <description>FreeRTOS</description>
      <originalPack>Amazon.FreeRTOS-Kernel.10.4.3-LTS.Patch.2+fsp.3.5.0.pack</originalPack>
    </component>
    <component apiversion="" class="Heaps" condition="" group="FreeRTOS" subgroup="heap_4" variant="" vendor="AWS" version="10.4.3-LTS.Patch.2+fsp.3.5.0">
      <description>FreeRTOS - Memory Management - Heap 4</description>
      <originalPack>Amazon.FreeRTOS-Kernel.10.4.3-LTS.Patch.2+fsp.3.5.0.pack</originalPack>
    </component>
    <component apiversion="" class="BSP" condition="" group="Board" subgroup="ra6m2_ek" variant="" vendor="Renesas" version="3.5.0">
      <description>RA6M2-EK Board Support Files</description>
      <originalPack>Renesas.RA_board_ra6m2_ek.3.5.0.pack</originalPack>
    </component>
    <component apiversion="" class="Common" condition="" group="all" subgroup="fsp_common" variant="" vendor="Renesas" version="3.5.0">
      <description>Board Support Package Common Files</description>
      <originalPack>Renesas.RA.3.5.0.pack</originalPack>
    </component>
    <component apiversion="" class="HAL Drivers" condition="" group="all" subgroup="r_dmac" variant="" vendor="Renesas" version="3.5.0">
      <description>Direct Memory Access Controller</description>
      <originalPack>Renesas.RA.3.5.0.pack</originalPack>
    </component>
    <component apiversion="" class="HAL Drivers" condition="" group="all" subgroup="r_ioport" variant="" vendor="Renesas" version="3.5.0">
      <description>I/O Port</description>
      <originalPack>Renesas.RA.3.5.0.pack</originalPack>
    </component>
    <component apiversion="" class="HAL Drivers" condition="" group="all" subgroup="r_sdhi" variant="" vendor="Renesas" version="3.5.0">
      <description>SD/MMC Host Interface</description>
      <originalPack>Renesas.RA.3.5.0.pack</originalPack>
    </component>
    <component apiversion="" class="Middleware" condition="" group="all" subgroup="rm_freertos_plus_fat" variant="" vendor="Renesas" version="3.5.0">
      <description>FreeRTOS+FAT Port for RA</description>
      <originalPack>Renesas.RA.3.5.0.pack</originalPack>
    </component>
    <component apiversion="" class="Middleware" condition="" group="all" subgroup="rm_block_media_sdmmc" variant="" vendor="Renesas" version="3.5.0">
      <description>SD/MMC Memory Implementation</description>
      <originalPack>Renesas.RA.3.5.0.pack</originalPack>
    </component>
    <component apiversion="" class="BSP" condition="" group="ra6m2" subgroup="device" variant="R7FA6M2AF3CFB" vendor="Renesas" version="3.5.0">
      <description>Board support package for R7FA6M2AF3CFB</description>
      <originalPack>Renesas.RA_mcu_ra6m2.3.5.0.pack</originalPack>
    </component>
    <component apiversion="" class="BSP" condition="" group="ra6m2" subgroup="device" variant="" vendor="Renesas" version="3.5.0">
      <description>Board support package for RA6M2</description>
      <originalPack>Renesas.RA_mcu_ra6m2.3.5.0.pack</originalPack>
    </component>
    <component apiversion="" class="BSP" condition="" group="ra6m2" subgroup="fsp" variant="" vendor="Renesas" version="3.5.0">
      <description>Board support package for RA6M2 - FSP Data</description>
      <originalPack>Renesas.RA_mcu_ra6m2.3.5.0.pack</originalPack>
    </component>
    <component apiversion="" class="Libraries" condition="" group="FreeRTOS_Plus" subgroup="FreeRTOS_Plus_FAT" variant="" vendor="AWS" version="3.5.0">
      <description>FreeRTOS Plus FAT</description>
      <originalPack>FreeRTOS.FreeRTOS_plus_FAT.3.5.0.pack</originalPack>
    </component>
    <component apiversion="" class="CMSIS" condition="" group="CMSIS5" subgroup="CoreM" variant="" vendor="Arm" version="5.8.0+renesas.0.fsp.3.5.0">
      <description>Arm CMSIS Version 5 - Core (M)</description>
      <originalPack>Arm.CMSIS5.5.8.0+renesas.0.fsp.3.5.0.pack</originalPack>
    </component>
  </raComponentSelection>
  <raElcConfiguration />
  <raIcuConfiguration />
  <raModuleConfiguration>
    <module id="module.driver.ioport_on_ioport.0">
      <property id="module.driver.ioport.name" value="g_ioport" />
      <property id="module.driver.ioport.elc_trigger_ioport1" value="_disabled" />
      <property id="module.driver.ioport.elc_trigger_ioport2" value="_disabled" />
      <property id="module.driver.ioport.elc_trigger_ioport3" value="_disabled" />
      <property id="module.driver.ioport.elc_trigger_ioport4" value="_disabled" />
      <property id="module.driver.ioport.pincfg" value="g_bsp_pin_cfg" />
    </module>
    <module id="module.freertos.freertosfat.968578683" />
    <module id="module.middleware.rm_freertos_plus_fat.240294532">
      <property id="module.middleware.rm_freertos_plus_fat.name" value="g_rm_freertos_plus_fat" />
      <property id="module.middleware.rm_freertos_plus_fat.num_sectors" value="31293440" />
      <property id="module.middleware.rm_freertos_plus_fat.sector_size" value="512" />
      <property id="module.middleware.rm_freertos_plus_fat.cache_size" value="1024" />
      <property id="module.middleware.rm_freertos_plus_fat.partition_number" value="0" />
      <property id="module.middleware.rm_freertos_plus_fat.callback" value="free_rtos_fat_callback" />
    </module>
    <module id="module.freertos.heap.4.240700696" />
    <module id="module.driver.rm_block_media_on_rm_block_media_sdmmc.317949711">
      <property id="module.driver.rm_block_media.name" value="g_rm_block_media" />
      <property id="module.driver.rm_block_media.callback" value="NULL" />
    </module>
    <module id="module.driver.sdmmc_on_sdmmc.1552612398">
      <property id="module.driver.sdmmc.name" value="g_sdmmc" />
      <property id="module.driver.sdmmc.channel" value="0" />
      <property id="module.driver.sdmmc.bus_width" value="module.driver.sdmmc.bus_width.bus_width_4_bits" />
      <property id="module.driver.sdmmc.block_size" value="512" />
      <property id="module.driver.sdmmc.card_detect" value="module.driver.sdmmc.card_detect.card_detect_cd" />
      <property id="module.driver.sdmmc.write_protect" value="module.driver.sdmmc.write_protect.write_protect_wp" />
      <property id="module.driver.sdmmc.p_callback" value="NULL" />
      <property id="module.driver.sdmmc.access_ipl" value="board.icu.common.irq.priority12" />
      <property id="module.driver.sdmmc.card_ipl" value="board.icu.common.irq.priority12" />
      <property id="module.driver.sdmmc.dma_req_ipl" value="_disabled" />
    </module>
    <module id="module.driver.transfer_on_dmac.1810903590">
      <property id="module.driver.transfer.name" value="g_transfer0" />
      <property id="module.driver.transfer.channel" value="0" />
      <property id="module.driver.transfer.mode" value="module.driver.transfer.mode.mode_normal" />
      <property id="module.driver.transfer.size" value="module.driver.transfer.size.size_2_byte" />
      <property id="module.driver.transfer.dest_addr_mode" value="module.driver.transfer.dest_addr_mode.addr_mode_fixed" />
      <property id="module.driver.transfer.src_addr_mode" value="module.driver.transfer.src_addr_mode.addr_mode_fixed" />
      <property id="module.driver.transfer.repeat_area" value="module.driver.transfer.repeat_area.repeat_area_source" />
      <property id="module.driver.transfer.p_dest" value="NULL" />
      <property id="module.driver.transfer.p_src" value="NULL" />
      <property id="module.driver.transfer.length" value="1" />
      <property id="module.driver.transfer.num_blocks" value="0" />
      <property id="module.driver.transfer.activation_event" value="enum.elc_none.none" />
      <property id="module.driver.transfer.p_callback" value="NULL" />
      <property id="module.driver.transfer.p_context" value="NULL" />
      <property id="module.driver.transfer.ipl" value="board.icu.common.irq.priority12" />
      <property id="module.driver.transfer.interrupt" value="module.driver.transfer.interrupt.interrupt_end" />
      <property id="module.driver.transfer.offset" value="1" />
      <property id="module.driver.transfer.src.buffer" value="1" />
    </module>
    <object id="rtos.awsfreertos.object.flags.698042606">
      <property id="rtos.awsfreertos.object.flags.symbol" value="g_SDHI_EventGroupHandle" />
      <property id="rtos.awsfreertos.object.flags.allocation" value="rtos.awsfreertos.object.flags.allocation.static" />
    </object>
    <context id="_hal.0">
      <stack module="module.driver.ioport_on_ioport.0" />
    </context>
    <context id="rtos.awsfreertos.thread.1149319170">
      <property id="_symbol" value="sdhi_thread" />
      <property id="rtos.awsfreertos.thread.name" value="SDHI Thread" />
      <property id="rtos.awsfreertos.thread.stack" value="4096" />
      <property id="rtos.awsfreertos.thread.priority" value="1" />
      <property id="rtos.awsfreertos.thread.context" value="NULL" />
      <property id="rtos.awsfreertos.thread.allocation" value="rtos.awsfreertos.thread.allocation.static" />
      <property id="rtos.awsfreertos.thread.secure_context" value="rtos.awsfreertos.thread.secure_context.enable" />
      <stack module="module.freertos.freertosfat.968578683">
        <stack module="module.middleware.rm_freertos_plus_fat.240294532" requires="module.freertos.freertosfat.requires.rm_freertos_plus_fat">
          <stack module="module.driver.rm_block_media_on_rm_block_media_sdmmc.317949711" requires="module.middleware.rm_freertos_plus_fat.requires.rm_block_media">
            <stack module="module.driver.sdmmc_on_sdmmc.1552612398" requires="module.driver.rm_block_media.requires.sdmmc">
              <stack module="module.driver.transfer_on_dmac.1810903590" requires="module.driver.sdmmc_on_sdmmc.requires.transfer" />
            </stack>
          </stack>
        </stack>
      </stack>
      <stack module="module.freertos.heap.4.240700696" />
    </context>
    <config id="config.driver.ioport">
      <property id="config.driver.ioport.checking" value="config.driver.ioport.checking.system" />
    </config>
    <config id="config.freertosplus.fat">
      <property id="config.freertosplus.fat.ffconfighas_cwd" value="config.freertosplus.fat.ffconfighas_cwd.enabled" />
      <property id="config.freertosplus.fat.ffconfigcwd_thread_local_index" value="0" />
      <property id="config.freertosplus.fat.ffconfiglfn_support" value="config.freertosplus.fat.ffconfiglfn_support.disabled" />
      <property id="config.freertosplus.fat.ffconfiginclude_short_name" value="config.freertosplus.fat.ffconfiginclude_short_name.disabled" />
      <property id="config.freertosplus.fat.ffconfigshortname_case" value="config.freertosplus.fat.ffconfigshortname_case.disabled" />
      <property id="config.freertosplus.fat.ffconfigunicode_utf16_support" value="config.freertosplus.fat.ffconfigunicode_utf16_support.disabled" />
      <property id="config.freertosplus.fat.ffconfigunicode_utf8_support" value="config.freertosplus.fat.ffconfigunicode_utf8_support.disabled" />
      <property id="config.freertosplus.fat.ffconfigfat12_support" value="config.freertosplus.fat.ffconfigfat12_support.disabled" />
      <property id="config.freertosplus.fat.ffconfigoptimise_unaligned_access" value="config.freertosplus.fat.ffconfigoptimise_unaligned_access.disabled" />
      <property id="config.freertosplus.fat.ffconfigcache_write_through" value="config.freertosplus.fat.ffconfigcache_write_through.disabled" />
      <property id="config.freertosplus.fat.ffconfigwrite_both_fats" value="config.freertosplus.fat.ffconfigwrite_both_fats.disabled" />
      <property id="config.freertosplus.fat.ffconfigwrite_free_count" value="config.freertosplus.fat.ffconfigwrite_free_count.disabled" />
      <property id="config.freertosplus.fat.ffconfigtime_support" value="config.freertosplus.fat.ffconfigtime_support.disabled" />
      <property id="config.freertosplus.fat.ffconfigremovable_media" value="config.freertosplus.fat.ffconfigremovable_media.disabled" />
      <property id="config.freertosplus.fat.ffconfigmount_find_free" value="config.freertosplus.fat.ffconfigmount_find_free.disabled" />
      <property id="config.freertosplus.fat.ffconfigfsinfo_trusted" value="config.freertosplus.fat.ffconfigfsinfo_trusted.disabled" />
      <property id="config.freertosplus.fat.ffconfigpath_cache" value="config.freertosplus.fat.ffconfigpath_cache.disabled" />
      <property id="config.freertosplus.fat.ffconfigpath_cache_depth" value="5" />
      <property id="config.freertosplus.fat.ffconfighash_cache" value="config.freertosplus.fat.ffconfighash_cache.disabled" />
      <property id="config.freertosplus.fat.ffconfighash_function" value="config.freertosplus.fat.ffconfighash_function.crc16" />
      <property id="config.freertosplus.fat.ffconfigmkdir_recursive" value="config.freertosplus.fat.ffconfigmkdir_recursive.disabled" />
      <property id="config.freertosplus.fat.ffconfigmalloc" value="pvPortMalloc" />
      <property id="config.freertosplus.fat.ffconfigfree" value="vPortFree" />
      <property id="config.freertosplus.fat.ffconfig64_num_support" value="config.freertosplus.fat.ffconfig64_num_support.disabled" />
      <property id="config.freertosplus.fat.ffconfigmax_partitions" value="4" />
      <property id="config.freertosplus.fat.ffconfigmax_file_sys" value="4" />
      <property id="config.freertosplus.fat.ffconfigdriver_busy_sleep_ms" value="20" />
      <property id="config.freertosplus.fat.ffconfigfprintf_support" value="config.freertosplus.fat.ffconfigfprintf_support.disabled" />
      <property id="config.freertosplus.fat.ffconfigfprintf_buffer_length" value="128" />
      <property id="config.freertosplus.fat.ff_printf" value="" />
      <property id="config.freertosplus.fat.ffconfiginline_memory_access" value="config.freertosplus.fat.ffconfiginline_memory_access.disabled" />
      <property id="config.freertosplus.fat.ffconfigfat_check" value="config.freertosplus.fat.ffconfigfat_check.disabled" />
      <property id="config.freertosplus.fat.ffconfigmax_filename" value="129" />
      <property id="config.freertosplus.fat.ffconfiguse_deltree" value="config.freertosplus.fat.ffconfiguse_deltree.disabled" />
    </config>
    <config id="config.awsfreertos.thread">
      <property id="config.awsfreertos.custom_freertosconfig" value="" />
      <property id="config.awsfreertos.thread.configuse_preemption" value="config.awsfreertos.thread.configuse_preemption.enabled" />
      <property id="config.awsfreertos.thread.configuse_port_optimised_task_selection" value="config.awsfreertos.thread.configuse_port_optimised_task_selection.disabled" />
      <property id="config.awsfreertos.thread.configuse_tickless_idle" value="config.awsfreertos.thread.configuse_tickless_idle.disabled" />
      <property id="config.awsfreertos.thread.configuse_idle_hook" value="config.awsfreertos.thread.configuse_idle_hook.enabled" />
      <property id="config.awsfreertos.thread.configuse_malloc_failed_hook" value="config.awsfreertos.thread.configuse_malloc_failed_hook.disabled" />
      <property id="config.awsfreertos.thread.configuse_daemon_task_startup_hook" value="config.awsfreertos.thread.configuse_daemon_task_startup_hook.disabled" />
      <property id="config.awsfreertos.thread.configuse_tick_hook" value="config.awsfreertos.thread.configuse_tick_hook.disabled" />
      <property id="config.awsfreertos.thread.configcpu_clock_hz" value="SystemCoreClock" />
      <property id="config.awsfreertos.thread.configtick_rate_hz" value="1000" />
      <property id="config.awsfreertos.thread.configmax_priorities" value="5" />
      <property id="config.awsfreertos.thread.configminimal_stack_size" value="128" />
      <property id="config.awsfreertos.thread.configmax_task_name_len" value="16" />
      <property id="config.awsfreertos.thread.configuse_trace_facility" value="config.awsfreertos.thread.configuse_trace_facility.disabled" />
      <property id="config.awsfreertos.thread.configuse_stats_formatting_functions" value="config.awsfreertos.thread.configuse_stats_formatting_functions.disabled" />
      <property id="config.awsfreertos.thread.configuse_16_bit_ticks" value="config.awsfreertos.thread.configuse_16_bit_ticks.disabled" />
      <property id="config.awsfreertos.thread.configidle_should_yield" value="config.awsfreertos.thread.configidle_should_yield.enabled" />
      <property id="config.awsfreertos.thread.configuse_task_notifications" value="config.awsfreertos.thread.configuse_task_notifications.enabled" />
      <property id="config.awsfreertos.thread.configuse_mutexes" value="config.awsfreertos.thread.configuse_mutexes.enabled" />
      <property id="config.awsfreertos.thread.configuse_recursive_mutexes" value="config.awsfreertos.thread.configuse_recursive_mutexes.enabled" />
      <property id="config.awsfreertos.thread.configuse_counting_semaphores" value="config.awsfreertos.thread.configuse_counting_semaphores.enabled" />
      <property id="config.awsfreertos.thread.configcheck_for_stack_overflow" value="config.awsfreertos.thread.configcheck_for_stack_overflow.disabled" />
      <property id="config.awsfreertos.thread.configqueue_registry_size" value="10" />
      <property id="config.awsfreertos.thread.configuse_queue_sets" value="config.awsfreertos.thread.configuse_queue_sets.disabled" />
      <property id="config.awsfreertos.thread.configuse_time_slicing" value="config.awsfreertos.thread.configuse_time_slicing.disabled" />
      <property id="config.awsfreertos.thread.configuse_newlib_reentrant" value="config.awsfreertos.thread.configuse_newlib_reentrant.disabled" />
      <property id="config.awsfreertos.thread.configenable_backward_compatibility" value="config.awsfreertos.thread.configenable_backward_compatibility.disabled" />
      <property id="config.awsfreertos.thread.confignum_thread_local_storage_pointers" value="5" />
      <property id="config.awsfreertos.thread.configstack_depth_type" value="uint32_t" />
      <property id="config.awsfreertos.thread.configmessage_buffer_length_type" value="size_t" />
      <property id="config.awsfreertos.thread.configsupport_static_allocation" value="config.awsfreertos.thread.configsupport_static_allocation.enabled" />
      <property id="config.awsfreertos.thread.configsupport_dynamic_allocation" value="config.awsfreertos.thread.configsupport_dynamic_allocation.enabled" />
      <property id="config.awsfreertos.thread.configtotal_heap_size" value="61440" />
      <property id="config.awsfreertos.thread.configapplication_allocated_heap" value="config.awsfreertos.thread.configapplication_allocated_heap.disabled" />
      <property id="config.awsfreertos.thread.configgenerate_run_time_stats" value="config.awsfreertos.thread.configgenerate_run_time_stats.disabled" />
      <property id="config.awsfreertos.thread.configuse_timers" value="config.awsfreertos.thread.configuse_timers.enabled" />
      <property id="config.awsfreertos.thread.configtimer_task_priority" value="3" />
      <property id="config.awsfreertos.thread.configtimer_queue_length" value="10" />
      <property id="config.awsfreertos.thread.configtimer_task_stack_depth" value="128" />
      <property id="config.awsfreertos.thread.configlibrary_max_syscall_interrupt_priority" value="board.icu.common.irq.priority1" />
      <property id="config.awsfreertos.thread.configassert" value="assert ( x )" />
      <property id="config.awsfreertos.thread.configinclude_application_defined_privileged_functions" value="config.awsfreertos.thread.configinclude_application_defined_privileged_functions.disabled" />
      <property id="config.awsfreertos.thread.include_vtaskpriorityset" value="config.awsfreertos.thread.include_vtaskpriorityset.enabled" />
      <property id="config.awsfreertos.thread.include_uxtaskpriorityget" value="config.awsfreertos.thread.include_uxtaskpriorityget.enabled" />
      <property id="config.awsfreertos.thread.include_vtaskdelete" value="config.awsfreertos.thread.include_vtaskdelete.enabled" />
      <property id="config.awsfreertos.thread.include_vtasksuspend" value="config.awsfreertos.thread.include_vtasksuspend.enabled" />
      <property id="config.awsfreertos.thread.include_xresumefromisr" value="config.awsfreertos.thread.include_xresumefromisr.enabled" />
      <property id="config.awsfreertos.thread.include_vtaskdelayuntil" value="config.awsfreertos.thread.include_vtaskdelayuntil.enabled" />
      <property id="config.awsfreertos.thread.include_vtaskdelay" value="config.awsfreertos.thread.include_vtaskdelay.enabled" />
      <property id="config.awsfreertos.thread.include_xtaskgetschedulerstate" value="config.awsfreertos.thread.include_xtaskgetschedulerstate.enabled" />
      <property id="config.awsfreertos.thread.include_xtaskgetcurrenttaskhandle" value="config.awsfreertos.thread.include_xtaskgetcurrenttaskhandle.enabled" />
      <property id="config.awsfreertos.thread.include_uxtaskgetstackhighwatermark" value="config.awsfreertos.thread.include_uxtaskgetstackhighwatermark.disabled" />
      <property id="config.awsfreertos.thread.include_xtaskgetidletaskhandle" value="config.awsfreertos.thread.include_xtaskgetidletaskhandle.disabled" />
      <property id="config.awsfreertos.thread.include_etaskgetstate" value="config.awsfreertos.thread.include_etaskgetstate.disabled" />
      <property id="config.awsfreertos.thread.include_xeventgroupsetbitfromisr" value="config.awsfreertos.thread.include_xeventgroupsetbitfromisr.enabled" />
      <property id="config.awsfreertos.thread.include_xtimerpendfunctioncall" value="config.awsfreertos.thread.include_xtimerpendfunctioncall.enabled" />
      <property id="config.awsfreertos.thread.include_xtaskabortdelay" value="config.awsfreertos.thread.include_xtaskabortdelay.disabled" />
      <property id="config.awsfreertos.thread.include_xtaskgethandle" value="config.awsfreertos.thread.include_xtaskgethandle.disabled" />
      <property id="config.awsfreertos.thread.include_xtaskresumefromisr" value="config.awsfreertos.thread.include_xtaskresumefromisr.enabled" />
      <property id="config.awsfreertos.thread.include_hw_stack_monitor" value="config.awsfreertos.thread.include_hw_stack_monitor.disabled" />
      <property id="config.awsfreertos.thread.print_function" value="printf(x)" />
      <property id="config.awsfreertos.thread.max_length" value="192" />
      <property id="config.awsfreertos.thread.include_time_and_task" value="config.awsfreertos.thread.include_time_and_task.disabled" />
    </config>
    <config id="config.driver.dmac">
      <property id="config.driver.dmac.param_checking_enable" value="config.driver.dmac.param_checking_enable.bsp" />
    </config>
    <config id="config.middleware.rm_freertos_plus_fat">
      <property id="config.middleware.rm_freertos_plus_fat.param_checking_enable" value="config.middleware.rm_freertos_plus_fat.param_checking_enable.bsp" />
    </config>
    <config id="config.driver.sdmmc">
      <property id="config.driver.sdmmc.param_checking_enable" value="config.driver.sdmmc.param_checking_enable.bsp" />
      <property id="config.driver.sdmmc.unaligned_support_enable" value="config.driver.sdmmc.unaligned_support_enable.enabled" />
      <property id="config.driver.sdmmc.sd_support_enable" value="config.driver.sdmmc.sd_support_enable.enabled" />
      <property id="config.driver.sdmmc.emmc_support_enable" value="config.driver.sdmmc.emmc_support_enable.disabled" />
    </config>
    <config id="config.driver.rm_block_media_sdmmc">
      <property id="config.driver.rm_block_media_sdmmc.param_checking_enable" value="config.driver.rm_block_media_sdmmc.param_checking_enable.bsp" />
    </config>
  </raModuleConfiguration>
  <raPinConfiguration>
    <pincfg active="true" name="RA6M2-EK.pincfg" selected="true" symbol="g_bsp_pin_cfg">
      <configSetting altId="adc1.an00.p004" configurationId="adc1.an00" />
      <configSetting altId="adc1.mode.custom" configurationId="adc1.mode" />
      <configSetting altId="debug0.mode.jtag" configurationId="debug0.mode" />
      <configSetting altId="debug0.tck.p300" configurationId="debug0.tck" />
      <configSetting altId="debug0.tdi.p110" configurationId="debug0.tdi" />
      <configSetting altId="debug0.tdo.p109" configurationId="debug0.tdo" />
      <configSetting altId="debug0.tms.p108" configurationId="debug0.tms" />
      <configSetting altId="p004.adc1.an00" configurationId="p004" />
      <configSetting altId="p004.gpio_mode.gpio_mode_an" configurationId="p004.gpio_mode" />
      <configSetting altId="p100.spi0.miso" configurationId="p100" />
      <configSetting altId="p100.gpio_mode.gpio_mode_peripheral" configurationId="p100.gpio_mode" />
      <configSetting altId="p101.spi0.mosi" configurationId="p101" />
      <configSetting altId="p101.gpio_mode.gpio_mode_peripheral" configurationId="p101.gpio_mode" />
      <configSetting altId="p102.spi0.rspck" configurationId="p102" />
      <configSetting altId="p102.gpio_mode.gpio_mode_peripheral" configurationId="p102.gpio_mode" />
      <configSetting altId="p105.input" configurationId="p105" />
      <configSetting altId="p105.gpio_irq.gpio_irq_enabled" configurationId="p105.gpio_irq" />
      <configSetting altId="p105.gpio_mode.gpio_mode_in" configurationId="p105.gpio_mode" />
      <configSetting altId="p106.output.low" configurationId="p106" />
      <configSetting altId="p106.gpio_mode.gpio_mode_out.low" configurationId="p106.gpio_mode" />
      <configSetting altId="p108.debug0.tms" configurationId="p108" />
      <configSetting altId="p108.gpio_mode.gpio_mode_peripheral" configurationId="p108.gpio_mode" />
      <configSetting altId="p109.debug0.tdo" configurationId="p109" />
      <configSetting altId="p109.gpio_mode.gpio_mode_peripheral" configurationId="p109.gpio_mode" />
      <configSetting altId="p110.debug0.tdi" configurationId="p110" />
      <configSetting altId="p110.gpio_mode.gpio_mode_peripheral" configurationId="p110.gpio_mode" />
      <configSetting altId="p205.sdhi0.dat3" configurationId="p205" />
      <configSetting altId="p205.gpio_speed.gpio_speed_high" configurationId="p205.gpio_drivecapacity" />
      <configSetting altId="p205.gpio_mode.gpio_mode_peripheral" configurationId="p205.gpio_mode" />
      <configSetting altId="p206.sdhi0.dat2" configurationId="p206" />
      <configSetting altId="p206.gpio_speed.gpio_speed_high" configurationId="p206.gpio_drivecapacity" />
      <configSetting altId="p206.gpio_mode.gpio_mode_peripheral" configurationId="p206.gpio_mode" />
      <configSetting altId="p209.sdhi0.wp" configurationId="p209" />
      <configSetting altId="p209.gpio_speed.gpio_speed_high" configurationId="p209.gpio_drivecapacity" />
      <configSetting altId="p209.gpio_mode.gpio_mode_peripheral" configurationId="p209.gpio_mode" />
      <configSetting altId="p210.sdhi0.cd" configurationId="p210" />
      <configSetting altId="p210.gpio_speed.gpio_speed_high" configurationId="p210.gpio_drivecapacity" />
      <configSetting altId="p210.gpio_mode.gpio_mode_peripheral" configurationId="p210.gpio_mode" />
      <configSetting altId="p300.debug0.tck" configurationId="p300" />
      <configSetting altId="p300.gpio_mode.gpio_mode_peripheral" configurationId="p300.gpio_mode" />
      <configSetting altId="p400.output.low" configurationId="p400" />
      <configSetting altId="p400.gpio_mode.gpio_mode_out.low" configurationId="p400.gpio_mode" />
      <configSetting altId="p401.sci7.txd" configurationId="p401" />
      <configSetting altId="p401.gpio_mode.gpio_mode_peripheral" configurationId="p401.gpio_mode" />
      <configSetting altId="p402.sci7.rxd" configurationId="p402" />
      <configSetting altId="p402.gpio_mode.gpio_mode_peripheral" configurationId="p402.gpio_mode" />
      <configSetting altId="p407.usbfs0.vbus" configurationId="p407" />
      <configSetting altId="p407.gpio_mode.gpio_mode_peripheral" configurationId="p407.gpio_mode" />
      <configSetting altId="p410.sdhi0.dat1" configurationId="p410" />
      <configSetting altId="p410.gpio_speed.gpio_speed_high" configurationId="p410.gpio_drivecapacity" />
      <configSetting altId="p410.gpio_mode.gpio_mode_peripheral" configurationId="p410.gpio_mode" />
      <configSetting altId="p411.sdhi0.dat0" configurationId="p411" />
      <configSetting altId="p411.gpio_speed.gpio_speed_high" configurationId="p411.gpio_drivecapacity" />
      <configSetting altId="p411.gpio_mode.gpio_mode_peripheral" configurationId="p411.gpio_mode" />
      <configSetting altId="p412.sdhi0.cmd" configurationId="p412" />
      <configSetting altId="p412.gpio_speed.gpio_speed_high" configurationId="p412.gpio_drivecapacity" />
      <configSetting altId="p412.gpio_mode.gpio_mode_peripheral" configurationId="p412.gpio_mode" />
      <configSetting altId="p413.sdhi0.clk" configurationId="p413" />
      <configSetting altId="p413.gpio_speed.gpio_speed_high" configurationId="p413.gpio_drivecapacity" />
      <configSetting altId="p413.gpio_mode.gpio_mode_peripheral" configurationId="p413.gpio_mode" />
      <configSetting altId="sci7.mode.asynchronous.free" configurationId="sci7.mode" />
      <configSetting altId="sci7.rxd.p402" configurationId="sci7.rxd" />
      <configSetting altId="sci7.txd.p401" configurationId="sci7.txd" />
      <configSetting altId="sdhi0.cd.p210" configurationId="sdhi0.cd" />
      <configSetting altId="sdhi0.clk.p413" configurationId="sdhi0.clk" />
      <configSetting altId="sdhi0.cmd.p412" configurationId="sdhi0.cmd" />
      <configSetting altId="sdhi0.dat0.p411" configurationId="sdhi0.dat0" />
      <configSetting altId="sdhi0.dat1.p410" configurationId="sdhi0.dat1" />
      <configSetting altId="sdhi0.dat2.p206" configurationId="sdhi0.dat2" />
      <configSetting altId="sdhi0.dat3.p205" configurationId="sdhi0.dat3" />
      <configSetting altId="sdhi0.mode.sd_mmc4mbit.free" configurationId="sdhi0.mode" />
      <configSetting altId="sdhi0.pairing.free" configurationId="sdhi0.pairing" />
      <configSetting altId="sdhi0.wp.p209" configurationId="sdhi0.wp" />
      <configSetting altId="spi0.miso.p100" configurationId="spi0.miso" />
      <configSetting altId="spi0.mode.enabled.a" configurationId="spi0.mode" />
      <configSetting altId="spi0.mosi.p101" configurationId="spi0.mosi" />
      <configSetting altId="spi0.rspck.p102" configurationId="spi0.rspck" />
      <configSetting altId="usbfs0.mode.device" configurationId="usbfs0.mode" />
      <configSetting altId="usbfs0.vbus.p407" configurationId="usbfs0.vbus" />
    </pincfg>
    <pincfg active="false" name="R7FA6M2AF3CFB.pincfg" selected="false" symbol="">
      <configSetting altId="debug0.mode.jtag" configurationId="debug0.mode" />
      <configSetting altId="debug0.tck.p300" configurationId="debug0.tck" />
      <configSetting altId="debug0.tdi.p110" configurationId="debug0.tdi" />
      <configSetting altId="debug0.tdo.p109" configurationId="debug0.tdo" />
      <configSetting altId="debug0.tms.p108" configurationId="debug0.tms" />
      <configSetting altId="p108.debug0.tms" configurationId="p108" />
      <configSetting altId="p108.gpio_mode.gpio_mode_peripheral" configurationId="p108.gpio_mode" />
      <configSetting altId="p109.debug0.tdo" configurationId="p109" />
      <configSetting altId="p109.gpio_mode.gpio_mode_peripheral" configurationId="p109.gpio_mode" />
      <configSetting altId="p110.debug0.tdi" configurationId="p110" />
      <configSetting altId="p110.gpio_mode.gpio_mode_peripheral" configurationId="p110.gpio_mode" />
      <configSetting altId="p300.debug0.tck" configurationId="p300" />
      <configSetting altId="p300.gpio_mode.gpio_mode_peripheral" configurationId="p300.gpio_mode" />
    </pincfg>
  </raPinConfiguration>
</raConfiguration>